Workbook

Sheet FEB
A1: TOTAL EXPENSE LIST | J1: AVAILABLE FROM PREVIOUS MONTH: | K1: 5840
A2: PAYMENT REASON | B2: PAYMENT CATEGORY | C2: DATE | D2: PAYMENT AMOUNT | J2: INCOME IN CURRENT MONTH: | K2: 45457
A3: Maa | B3: EMI | C3: =DATE(2022,2,6) -> 44598 | D3: 15000 | J3: INTEREST EARN | K3: 40
A4: SIP | B4: INVEST | C4: =DATE(2022,1,31) -> 44592 | D4: 5000
A5: MOBILE | B5: EMI | C5: =DATE(2022,1,31) -> 44592 | D5: 1300 | J5: TOTAL AVAILABLE: | K5: =SUM(K1:K3) -> 51337
A6: AC | B6: EMI | C6: =DATE(2022,1,31) -> 44592 | D6: 4000
A7: ARGHYA | B7: EMI | C7: =DATE(2022,1,31) -> 44592 | D7: 2000 | J7: AVAILABLE BALANCE: | K7: =K5 - (D26) -> 4319
A8: SMALL PARTY (MOGLAI) | B8: PARTY | C8: =DATE(2022,1,31) -> 44592 | D8: 500
A9: EYE | B9: MEDICAL | C9: =DATE(2022,1,31) -> 44592 | D9: 1500
A10: BABA | B10: PARTY | C10: =DATE(2022,1,31) -> 44592 | D10: 3000
A11: FD | B11: INVEST | C11: =DATE(2022,1,31) -> 44592 | D11: 5000
A12: ELECTRIC BILL | B12: BILL | C12: =DATE(2022,2,1) -> 44593 | D12: 3420
A13: Mobile Recharge (8653640704) | B13: MOBILE BILL | C13: =DATE(2022,2,3) -> 44595 | D13: 99
A14: Hot Gel Pad | B14: MEDICAL | C14: =DATE(2022,2,3) -> 44595 | D14: 179
A15: Rini | B15: PARTY | C15: =DATE(2022,2,6) -> 44598 | D15: 3000
A16: Mobile Recharge (8617414770) | B16: MOBILE BILL | C16: =DATE(2022,2,8) -> 44600 | D16: 99
A17: Mobile Recharge (9434825579) | B17: MOBILE BILL | C17: =DATE(2022,2,8) -> 44600 | D17: 155
A18: Mobile Recharge (9333818130) | B18: MOBILE BILL | C18: =DATE(2022,2,11) -> 44603 | D18: 99
A19: Mobile Recharge (8918405876) | B19: MOBILE BILL | C19: =DATE(2022,2,12) -> 44604 | D19: 155
A20: Thesis Project expense | B20: EDUCATION | C20: =DATE(2022,2,12) -> 44604 | D20: 1000
A21: WIFI | B21: BILL | C21: =DATE(2022,2,13) -> 44605 | D21: 1357
A22: Mobile Recharge (6296963476) | B22: MOBILE BILL | C22: =DATE(2022,2,20) -> 44612 | D22: 155
C26: TOTAL EXPENSE | D26: =SUM(D3:D24) -> 47018
A28: PENDING
A29: PAYMENT REASON | B29: PAYMENT CATEGORY | D29: PAYMENT AMOUNT
C38: PENDING EXPENSE | D38: =SUM(D21:D36) -> 48530

Sheet MAR
A1: TOTAL EXPENSE LIST | G1: AVAILABLE FROM PREVIOUS MONTH: | H1: =FEB!K7 -> 4319
A2: PAYMENT REASON | B2: PAYMENT CATEGORY | C2: DATE | D2: PAYMENT AMOUNT | G2: INCOME IN CURRENT MONTH: | H2: =40000+1357 -> 41357
A3: Maa | B3: EMI | C3: =DATE(2022, 2, 26) -> 44618 | D3: 12000 | G3: Savings add | H3: 18000
A4: Arghya (Trade mil & screen) | B4: EMI | C4: =DATE(2022, 2, 27) -> 44619 | D4: 2500 | G4: Ticket Pending | H4: 1300
A5: Arghya (Scooty) | B5: EMI | C5: =DATE(2022, 2, 27) -> 44619 | D5: 2860 | G5: TOTAL AVAILABLE: | H5: =H1 + H2 + H3 -> 63676
A6: Electric bill | B6: BILL | C6: =DATE(2022, 2, 27) -> 44619 | D6: 3330 | J6: Expected Avail. Bal: | K6: =H7 - D47 -> 20232.5
A7: SIP | B7: INVESTMENT | C7: 44619 | D7: 4700 | G7: AVAILABLE BALANCE: | H7: =H5 - (D27) -> 20232.5
A8: FD | B8: INVESTMENT | C8: 44619 | D8: 5000
A9: MOBILE | B9: EMI | C9: 44620 | D9: 1300
A10: Cook | B10: FAMILY | C10: 44620 | D10: 1000
A11: iAloy HW | B11: PROJECT | C11: 44620 | D11: 3000
A12: Cash | B12: PERSONAL | C12: 44620 | D12: 500
A13: Mobile Recharge (8653640704) | B13: MOBILE BILL | C13: =DATE(2022,3,3) -> 44623 | D13: 99
A14: Mobile Recharge (8617414770) | B14: MOBILE BILL | C14: =DATE(2022,3,10) -> 44630 | D14: 155 | G14: BERHAMPORE TRIP
A15: Mobile Recharge (9046266900) | B15: MOBILE BILL | C15: =DATE(2022,3,10) -> 44630 | D15: 99 | G15: Train ticket(knj-bpc) | H15: =DATE(2022,3,11) -> 44631 | I15: 142 | K15: D
A16: Mobile Recharge (8918405876) | B16: MOBILE BILL | C16: =DATE(2022,3,10) -> 44630 | D16: 155 | G16: Train ticket(bpc-knj) | H16: =DATE(2022,3,11) -> 44631 | I16: 50 | K16: D
A17: Mobile Recharge (9333818130) | B17: MOBILE BILL | C17: =DATE(2022,3,10) -> 44630 | D17: 99 | G17: Lunch | I17: 1924 | K17: A
A18: WiFi | B18: BILL | C18: =DATE(2022,3,15) -> 44635 | D18: 1357 | G18: Dinner | I18: 1800 | K18: D
A19: Train Ticket(Puri) | C19: =DATE(2022,3,12) -> 44632 | D19: 1227 | G19: Toto night | I19: 80 | J19: Arghya | K19: A
A20: Train Ticket(BPC) | B20: Berhampore | D20: 142.5 | G20: Canteene | I20: 500 | K20: D
A21: Hotpot | B21: Berhampore | D21: 650 | G21: Guest room | I21: 400 | K21: A
A22: Cash | D22: 1000 | G22: Lunch | I22: 800 | J22: Arghya | K22: A
A23: Table Fan | C23: =DATE(2022,3,19) -> 44639 | D23: 900 | G23: Blue wave | I23: 356
A24: Arghya | B24: Berhampore | C24: =DATE(2022,3,31) -> 44651 | D24: 735
A25: HotStar recharge | B25: BILL | C25: =DATE(2022,3,27) -> 44647 | D25: 635
C27: TOTAL EXPENSE | D27: =SUM(D3:D25) -> 43443.5 | L27: 2292
G28: TOTAL | I28: =sum(I15:I26) -> 6052 | L28: 3760 | M28: 236
A30: PENDING | I30: =(I28/2) -> 3026
A31: PAYMENT REASON | B31: PAYMENT CATEGORY | D31: PAYMENT AMOUNT | I31: =(I30+650) -> 3676
C47: PENDING EXPENSE | D47: =SUM(D32:D45) -> 0

Sheet APR
A1: TOTAL EXPENSE LIST | G1: AVAILABLE FROM PREVIOUS MONTH: | H1: =MAR!H7 -> 20232.5
A2: PAYMENT REASON | B2: PAYMENT CATEGORY | C2: DATE | D2: PAYMENT AMOUNT | G2: INCOME IN CURRENT MONTH: | H2: 41357
A3: Electronics | B3: TECH | C3: =DATE(2022,3,29) -> 44649 | D3: 1144.84 | G3: Interest Earn | H3: 81
A4: Mobile Recharge (8653640704) | B4: MOBILE BILL | C4: =DATE(2022,3,30) -> 44650 | D4: 99
A5: Arghya (Scooty) | B5: EMI | C5: =DATE(2022,3,31) -> 44651 | D5: 2350
A6: SIP | B6: INVESTMENT | C6: =DATE(2022,3,31) -> 44651 | D6: 5000 | G6: TOTAL AVAILABLE: | H6: =SUM(H1:H4) -> 61670.5
A7: FD | B7: INVESTMENT | C7: =DATE(2022,3,31) -> 44651 | D7: 5000
A8: Electric bill | B8: BILL | C8: =DATE(2022,3,31) -> 44651 | D8: 3318 | G8: AVAILABLE BALANCE: | H8: =H6 - (D31) -> 17960.66
A9: Fan | B9: FAMILY | C9: =DATE(2022,3,31) -> 44651 | D9: 1337 | G9: Expected Avail. Bal: | H9: =H8 - D54 -> 17310.66
A10: Damma medicine | B10: FAMILY | C10: =DATE(2022,4,10) -> 44661 | D10: 2000
A11: MOBILE | B11: EMI | C11: =DATE(2022,4,1) -> 44652 | D11: 1300
A12: MAA | B12: EMI | C12: =DATE(2022,4,1) -> 44652 | D12: 13000
A13: Cook | B13: FAMILY | C13: =DATE(2022,4,1) -> 44652 | D13: 1000
A14: In Hand | B14: PERSONAL | C14: =DATE(2022,4,1) -> 44652 | D14: 1400
A15: Shopping | B15: PERSONAL | C15: =DATE(2022,4,2) -> 44653 | D15: 3478
A16: Mobile Recharge (8918405876) | B16: MOBILE BILL | C16: =DATE(2022,3,30) -> 44650 | D16: 155
A17: Mobile Recharge (8617414770) | B17: MOBILE BILL | C17: =DATE(2022,3,30) -> 44650 | D17: 155
A18: Mobile Recharge (9333818130) | B18: MOBILE BILL | C18: =DATE(2022,4,11) -> 44662 | D18: 99
A19: WiFi | B19: BILL | C19: =DATE(2022,4,14) -> 44665 | D19: 1357
A20: HeadPhone | B20: PERSONAL | C20: =DATE(2022,4,11) -> 44662 | D20: 180
A21: Light | B21: FAMILY | C21: =DATE(2022,4,18) -> 44669 | D21: 330
A22: Medical form fillup | B22: RINI | C22: =DATE(2022,4,27) -> 44678 | D22: 900
A23: Mobile Recharge (8653640704) | B23: MOBILE BILL | C23: =DATE(2022,4,26) -> 44677 | D23: 99
A24: Misc. | D24: 8
C31: TOTAL EXPENSE | D31: =SUM(D3:D29) -> 43709.84
A34: PENDING
A35: PAYMENT REASON | B35: PAYMENT CATEGORY | D35: PAYMENT AMOUNT
A38: Arghya (Screen) | B38: EMI | D38: 650
C54: PENDING EXPENSE | D54: =SUM(D36:D52) -> 650

Sheet MAY
A1: TOTAL EXPENSE LIST | J1: AVAILABLE FROM PREVIOUS MONTH: | K1: =APR!H8 -> 17960.66
A2: PAYMENT REASON | B2: PAYMENT CATEGORY | C2: DATE | D2: PAYMENT AMOUNT | J2: INCOME IN CURRENT MONTH: | K2: 40000
A3: Rini Unacademy | B3: EDUCATION | C3: =DATE(2022,4,29) -> 44680 | D3: 239 | J3: TOTAL AVAILABLE: | K3: =K1 + K2 -> 57960.66
A4: Arghya (Scooty) | B4: EMI | C4: =DATE(2022,4,30) -> 44681 | D4: 2350
A5: Bangalore | B5: HOME RENT | C5: =DATE(2022,4,30) -> 44681 | D5: 20000 | J5: AVAILABLE BALANCE: | K5: =K3 - (D26) -> 2326.62
A6: SIP | B6: INVESTMENT | C6: =DATE(2022,4,30) -> 44681 | D6: 5000 | J6: Expected Avail. Bal: | K6: =K5 - D48 -> -56836.17
A7: FD | B7: INVESTMENT | C7: =DATE(2022,4,30) -> 44681 | D7: 5000
A8: Electric bill | B8: BILL | C8: =DATE(2022,4,30) -> 44681 | D8: 4069
A9: Extra SIP | B9: TEMP | C9: =DATE(2022,4,30) -> 44681 | D9: 500
A10: MAA | B10: EMI | C10: =DATE(2022,5,1) -> 44682 | D10: 8000
A11: Cook | B11: FAMILY | C11: =DATE(2022,5,1) -> 44682 | D11: 1000
A12: In Hand | B12: PERSONAL | C12: =DATE(2022,5,1) -> 44682 | D12: =200+380+1000 -> 1580
A13: Mother's Hut | B13: FAMILY | C13: =DATE(2022,4,30) -> 44681 | D13: 1900
A14: Berhampore | B14: SOCIAL | C14: =DATE(2022,5,7) -> 44688 | D14: =(842+860+260+500) -> 2462
A15: Misc | D15: 5.29
A16: WiFi | B16: BILL | C16: =DATE(2022,5,14) -> 44695 | D16: 1357
A17: Mobile recharge(8918405876) | B17: BILL | D17: 155
A18: Mobile recharge(8653640704) | B18: BILL | D18: 99
A19: Mobile recharge(8918405876) | B19: BILL | D19: 155
A20: TEMP | D20: =(75+126.8+478.95+155+155+99+50+240)-1000 -> 379.75
A21: Mobile recharge(9434825579) | B21: BILL | D21: 607
A22: Cinema | D22: 130
A23: Misc | D23: 646
C26: TOTAL EXPENSE | D26: =SUM(D3:D24) -> 55634.04
A29: PENDING
A30: PAYMENT REASON | B30: PAYMENT CATEGORY | D30: PAYMENT AMOUNT
C48: PENDING EXPENSE | D48: =SUM(D16:D45) -> 59162.79

Sheet JUN
A1: TOTAL EXPENSE LIST | J1: AVAILABLE FROM PREVIOUS MONTH: | K1: =MAY!K5 -> 2326.62
A2: PAYMENT REASON | B2: PAYMENT CATEGORY | C2: DATE | D2: PAYMENT AMOUNT | J2: INCOME IN CURRENT MONTH: | K2: 41357
A3: Arghya (Scooty) | B3: EMI | D3: 2350 | J3: TOTAL AVAILABLE: | K3: =K1 + K2 -> 43683.62
A4: Electric bill | B4: BILL | D4: 4106
A5: In Hand | B5: PERSONAL | D5: 500 | J5: AVAILABLE BALANCE: | K5: =K3 - (D26) -> 2967.12
A6: Bangalore | B6: HOME RENT | C6: =DATE(2022,4,30) -> 44681 | D6: 6000
A7: MAA | B7: EMI | D7: 8000
A8: Cook | B8: FAMILY | D8: 1000
A9: SIP | B9: INVESTMENT | D9: 5000
A11: Conference | B11: EDUCATION | D11: 4612.5
A12: Water Purifier | B12: FAMILY | D12: 3300
A13: Rini HS Review | D13: 900
A14: Mislenous | D14: 4948
C26: TOTAL EXPENSE | D26: =SUM(D3:D24) -> 40716.5
A29: PENDING
A30: PAYMENT REASON | B30: PAYMENT CATEGORY | D30: PAYMENT AMOUNT
A33: WiFi | B33: BILL | D33: 1357
A34: MOBILE RECHARGE | B34: BILL | D34: 607
A37: FD | B37: INVESTMENT | D37: 5000
C48: PENDING EXPENSE | D48: =SUM(D7:D46) -> 75441
A53: Arghya (Screen) | B53: EMI | D53: 650

Sheet JUL
A1: TOTAL EXPENSE LIST | J1: AVAILABLE FROM PREVIOUS MONTH: | K1: =JUN!K5 -> 2967.12
A2: PAYMENT REASON | B2: PAYMENT CATEGORY | C2: DATE | D2: PAYMENT AMOUNT | J2: INCOME IN CURRENT MONTH: | K2: 40000
A3: SSD | D3: 1300 | J3: KAKA | K3: 15000
A4: Arghya (Scooty) | B4: EMI | D4: 2350 | J4: TOTAL AVAILABLE: | K4: =K1 + K2 + K3 -> 57967.12
A5: Bangalore | B5: HOME RENT | D5: 6000
A6: Electric bill | B6: BILL | D6: 4103 | J6: AVAILABLE BALANCE: | K6: =K4 - (D31) -> 34137.67
A7: SIP | B7: INVESTMENT | D7: 2000 | J7: EXP AVAILABLE BALANCE: | K7: =K4 - (D32) - D55 -> 48658.12
A8: CASH | B8: TEMP | D8: =(422.5 + 1509.65 + 1034.3 + 25) - 570 -> 2421.45
A9: Arghya (Flight) | B9: BILL | D9: 3000
A10: Mobile recharge(8918405876) | B10: BILL | D10: 155
A11: SIP | B11: TEMP | D11: 2500
C31: TOTAL EXPENSE | D31: =SUM(D3:D29) -> 23829.45
A34: PENDING
A35: PAYMENT REASON | B35: PAYMENT CATEGORY | D35: PAYMENT AMOUNT
A38: In Hand | B38: PERSONAL | D38: 500
A40: MAA | B40: EMI | D40: 6000
A41: Cook | B41: FAMILY | D41: 1000
A43: WiFi | B43: BILL | D43: 1357
A44: MOBILE RECHARGE | B44: BILL | D44: =607 - (155) -> 452
A46: Kurukshetra
C55: PENDING EXPENSE | D55: =SUM(D36:D53) -> 9309

Sheet AUG
A1: TOTAL EXPENSE LIST | J1: AVAILABLE FROM PREVIOUS MONTH: | K1: 1530
A2: PAYMENT REASON | B2: PAYMENT CATEGORY | C2: DATE | D2: PAYMENT AMOUNT | J2: INCOME IN CURRENT MONTH: | K2: =(193737 + 1357) -> 195094
A3: Pujo | B3: PUJO | C3: =DATE(2022, 7, 27) -> 44769 | D3: 15000 | J3: TOTAL AVAILABLE: | K3: =K1 + K2 -> 196624
A4: Cash | B4: CASH | C4: =DATE(2022, 7, 27) -> 44769 | D4: 500
A5: Chawala | B5: SOCIAL | C5: =DATE(2022, 7, 27) -> 44769 | D5: =(398+149) -> 547 | J5: CURRENT AVAILABLE BALANCE: | K5: =K3 - (D43) -> 89488
A6: Flat rent | B6: BANGALORE | C6: =DATE(2022, 7, 29) -> 44771 | D6: 10500 | J6: EXPECTED AVAILABLE BALANCE: | K6: =K5 - D62 + SUM(D19:D21) -> -124657
A7: Arghya (Scooty) | B7: EMI | C7: =DATE(2022, 7, 29) -> 44771 | D7: 2350
A8: Arghya | B8: PENDING | C8: =DATE(2022, 7, 29) -> 44771 | D8: =(5000+2000+1300) -> 8300
A9: Electric bill | B9: BILL | C9: =DATE(2022, 7, 29) -> 44771 | D9: 5763
A10: SIP | B10: INVESTMENT | C10: =DATE(2022, 7, 29) -> 44771 | D10: 5000
A11: FD | B11: INVESTMENT | C11: =DATE(2022, 7, 29) -> 44771 | D11: 10000
A12: Mobile recharge(8918405876) | B12: BILL | C12: =DATE(2022, 7, 29) -> 44771 | D12: 155
A13: Karkhana repair | B13: HOME | C13: =DATE(2022, 7, 29) -> 44771 | D13: 5800
A14: Mobile recharge(9333818130) | B14: BILL | C14: =DATE(2022, 7, 30) -> 44772 | D14: 99
A15: Flight Booking | B15: BANGALORE | C15: =DATE(2022, 7, 31) -> 44773 | D15: 13502
A16: Jeevansathi.com | B16: SUBSCRIPTION | C16: =DATE(2022, 7, 31) -> 44773 | D16: 692
A17: MAA | B17: EMI | C17: =DATE(2022, 7, 31) -> 44773 | D17: 16000
A18: Cook | B18: FAMILY | C18: =DATE(2022, 7, 31) -> 44773 | D18: 3000
A19: Pujo | B19: PUJO | C19: =DATE(2022, 7, 27) -> 44769 | D19: 7500
A20: Foldable wordrobe | B20: FAMILY | C20: =DATE(2022, 8, 1) -> 44774 | D20: 1279
A21: Fuchka | B21: FAMILY | D21: =(210+60+80) -> 350
A22: Cha Khor | B22: FAMILY | C22: =DATE(2022, 8, 1) -> 44774 | D22: 200
A23: Mobile recharge(9046266900) | B23: BILL | C23: =DATE(2022, 7, 30) -> 44772 | D23: 99
A24: Mobile recharge(9333818130) | B24: BILL | C24: =DATE(2022, 8, 7) -> 44780 | D24: 100
A25: Extra Paytm | B25: BILL | C25: =DATE(2022, 8, 7) -> 44780 | D25: 400
C43: TOTAL EXPENSE | D43: =SUM(D3:D40) -> 107136
A46: PENDING
A47: PAYMENT REASON | B47: PAYMENT CATEGORY | D47: PAYMENT AMOUNT
A50: WiFi | B50: BILL | D50: 1357
A51: MOBILE RECHARGE | B51: BILL | D51: =(607 - (D12 + D14)) -> 353
A52: Technical expenses | B52: TECHNICAL | D52: 8000
A54: Pujo | B54: PUJO | D54: =(100000 - (D3 + D19)) -> 77500
C62: PENDING EXPENSE | D62: =SUM(D17:D60) -> 223274
A66: Arghya | B66: PENDING | D66: =(30000) -> 30000
A67: Kaka | B67: PENDING | D67: =(15000+10000+5000) -> 30000

Sheet SEP
A1: TOTAL EXPENSE LIST | J1: AVAILABLE FROM PREVIOUS MONTH: | K1: 1530
A2: PAYMENT REASON | B2: PAYMENT CATEGORY | C2: DATE | D2: PAYMENT AMOUNT | J2: INCOME IN CURRENT MONTH: | K2: =(193737 + 1357) -> 195094
A3: Pujo | B3: PUJO | C3: =DATE(2022, 7, 27) -> 44769 | D3: 15000 | J3: TOTAL AVAILABLE: | K3: =K1 + K2 -> 196624
A4: Cash | B4: CASH | C4: =DATE(2022, 7, 27) -> 44769 | D4: 500
A5: Chawala | B5: SOCIAL | C5: =DATE(2022, 7, 27) -> 44769 | D5: =(398+149) -> 547 | J5: CURRENT AVAILABLE BALANCE: | K5: =K3 - (D34) -> 118209
A6: Flat rent | B6: BANGALORE | C6: =DATE(2022, 7, 29) -> 44771 | D6: 10500 | J6: EXPECTED AVAILABLE BALANCE: | K6: =K5 - D59 + SUM(D13:D16) -> 17900
A7: Arghya (Scooty) | B7: EMI | C7: =DATE(2022, 7, 29) -> 44771 | D7: 2350
A8: Arghya | B8: PENDING | C8: =DATE(2022, 7, 29) -> 44771 | D8: =(5000+2000+1300) -> 8300
A9: Electric bill | B9: BILL | C9: =DATE(2022, 7, 29) -> 44771 | D9: 5763
A10: SIP | B10: INVESTMENT | C10: =DATE(2022, 7, 29) -> 44771 | D10: 5000
A11: FD | B11: INVESTMENT | C11: =DATE(2022, 7, 29) -> 44771 | D11: 10000
A12: Mobile recharge(8918405876) | B12: BILL | C12: =DATE(2022, 7, 29) -> 44771 | D12: 155
A13: SIP (KAKA) | B13: TEMP | C13: =DATE(2022, 7, 29) -> 44771 | D13: =(2500) -> 2500
A14: TV | B14: TEMP | C14: =DATE(2022, 7, 29) -> 44771 | D14: =(1000) -> 1000
A15: Gold loan | B15: TEMP | C15: =DATE(2022, 7, 29) -> 44771 | D15: 4000
A16: Unacademy | B16: TEMP | C16: =DATE(2022, 7, 29) -> 44771 | D16: 3000
A17: Karkhana repair | B17: HOME | C17: =DATE(2022, 7, 29) -> 44771 | D17: 5800
A18: Arghya (Setup) | B18: EMI | C18: =DATE(2022, 8, 27) -> 44800 | D18: 4000
C34: TOTAL EXPENSE | D34: =SUM(D3:D32) -> 78415
A37: PENDING
A38: PAYMENT REASON | B38: PAYMENT CATEGORY | D38: PAYMENT AMOUNT
A39: MAA | B39: EMI | D39: 15000
A40: Cook | B40: FAMILY | D40: 1000
A41: WiFi | B41: BILL | D41: 1357
A42: MOBILE RECHARGE | B42: BILL | D42: =(607 - (D12)) -> 452
A43: Technical expenses | B43: TECHNICAL | D43: 8000
A45: Pujo | B45: PUJO | D45: =(100000 - D3) -> 85000
C59: PENDING EXPENSE | D59: =SUM(D39:D57) -> 110809
A63: Arghya | B63: PENDING | D63: =(30000) -> 30000
A64: Kaka | B64: PENDING | D64: =(15000+10000+5000) -> 30000

Sheet OCT
A1: TOTAL EXPENSE LIST | J1: AVAILABLE FROM PREVIOUS MONTH: | K1: 2185
A2: PAYMENT REASON | B2: PAYMENT CATEGORY | C2: DATE | D2: PAYMENT AMOUNT | J2: INCOME IN CURRENT MONTH: | K2: 87045
A3: MAA | B3: EMI | C3: =DATE(2022, 9, 29) -> 44833 | D3: 500 | J3: TOTAL AVAILABLE: | K3: =K1 + K2 -> 89230
A4: PW-Rini | B4: EDUCATION | C4: =DATE(2022, 9, 29) -> 44833 | D4: 4149
A5: Ice-Cream | B5: FAMILY | C5: =DATE(2022, 9, 28) -> 44832 | D5: 220 | J5: CURRENT AVAILABLE BALANCE: | K5: =K3 - (D34) -> 1472
A6: Flat rent | B6: BANGALORE | C6: =DATE(2022, 9, 30) -> 44834 | D6: 7500
A7: Arghya (Scooty) | B7: EMI | C7: =DATE(2022, 9, 30) -> 44834 | D7: 2350
A8: UTI-SIP | B8: SAVINGS | C8: =DATE(2022, 9, 30) -> 44834 | D8: 2000 | J8: Return from KAKA | K8: =(D11 + D16 ) -> 5147
A9: SIP | B9: SAVINGS | C9: =DATE(2022, 9, 30) -> 44834 | D9: 3000
A10: SAVINGS | B10: SAVINGS | C10: =DATE(2022, 9, 30) -> 44834 | D10: 10000 | J10: EXPECTED AVAILABLE BALANCE: | K10: =K5 - D59 + K8 -> 928
A11: SIP-KAKA | B11: TEMP | C11: =DATE(2022, 9, 30) -> 44834 | D11: 2500
A12: Jogodhatri Pujo | B12: PUJO | C12: =DATE(2022, 9, 30) -> 44834 | D12: 13000 | E12: Transfered to Joint A/C
A13: Kali Pujo | B13: PUJO | C13: =DATE(2022, 9, 30) -> 44834 | D13: 3000
A14: Electricity | B14: FAMILY | C14: =DATE(2022, 9, 30) -> 44834 | D14: 5763 | J14: Pujo Expense estimate | K14: =D12 -> 13000
A15: Mobile (EMI) | B15: EMI | C15: =DATE(2022, 10, 2) -> 44836 | D15: 3648
A16: Rini | B16: TEMP | C16: =DATE(2022, 10, 2) -> 44836 | D16: 2647 | J16: PUJO EXPENSES
A17: Chawala | B17: Social | C17: =DATE(2022, 9, 30) -> 44834 | D17: 248 | J17: Sajh advance | K17: =DATE(2022, 10, 6) -> 44840 | L17: 2001
A18: Mobile Recharge(7908760756) | B18: BILL | C18: =DATE(2022, 10, 5) -> 44839 | D18: 155 | J18: Electrical expenses | L18: 2500
A19: Mobile Recharge(8653640704) | B19: BILL | C19: =DATE(2022, 10, 5) -> 44839 | D19: 99
A20: Mobile Recharge(9333818130) | B20: BILL | C20: =DATE(2022, 10, 5) -> 44839 | D20: 99
A21: Cash | B21: PERSONAL | C21: =DATE(2022, 10, 2) -> 44836 | D21: 1500
A22: Paytm | B22: PERSONAL | C22: =DATE(2022, 10, 5) -> 44839 | D22: 100
A23: MAA | B23: EMI | C23: =DATE(2022, 10, 5) -> 44839 | D23: 12000
A24: Cook | B24: FAMILY | C24: =DATE(2022, 10, 5) -> 44839 | D24: 1000
A25: Flight Bangalore | B25: TRAVEL | C25: =DATE(2022, 10, 6) -> 44840 | D25: 6545
A26: Train KNJ_SDAH | B26: TRAVEL | C26: =DATE(2022, 10, 6) -> 44840 | D26: 141
A27: Barir Kaj | B27: FAMILY | C27: =DATE(2022, 10, 11) -> 44845 | D27: 1610
A28: Transfer to PayTM | B28: PERSONAL | C28: =DATE(2022, 10, 8) -> 44842 | D28: 452 | J28: Total Pujo Expenses | L28: =SUM(L17:L26) -> 4501
A29: Chowmin | B29: FAMILY | C29: =DATE(2022, 10, 10) -> 44844 | D29: 318 | J29: Remaining in Hand | L29: =K14-L28 -> 8499
A30: BhaiPhota gift | B30: FAMILY | C30: =DATE(2022, 10, 25) -> 44859 | D30: 700
A31: Food & Icecream | B31: PERSONAL | C31: =DATE(2022, 10, 25) -> 44859 | D31: 289
A32: Mislenious | D32: 2225
C34: TOTAL EXPENSE | D34: =SUM(D3:D32) -> 87758
A37: PENDING
A38: PAYMENT REASON | B38: PAYMENT CATEGORY | D38: PAYMENT AMOUNT
A39: WiFi | B39: BILL | D39: 1357
A40: MOBILE RECHARGE | B40: BILL | D40: =(762 - (D18 + D19 + D20)) -> 409
A41: Technical expenses | B41: TECHNICAL | D41: 2000
A42: Arghya (EMI Chair) | B42: EMI | D42: 1925
C59: PENDING EXPENSE | D59: =SUM(D38:D57) -> 5691
A64: Kaka | B64: PENDING | D64: =(15000+10000+5000) -> 30000

Sheet NOV
A1: TOTAL EXPENSE LIST | J1: AVAILABLE FROM PREVIOUS MONTH: | K1: =OCT!K1 -> 2185
A2: PAYMENT REASON | B2: PAYMENT CATEGORY | C2: DATE | D2: PAYMENT AMOUNT | J2: INCOME IN CURRENT MONTH: | K2: 134092
A3: SIP | B3: SAVINGS | C3: =DATE(2022, 10, 28) -> 44862 | D3: 3000 | J3: NLC Return | K3: 144
A4: SAVINGS | B4: SAVINGS | C4: =DATE(2022, 10, 28) -> 44862 | D4: 34000 | J4: TOTAL AVAILABLE: | K4: =K1 + K2 + K3 -> 136421
A5: SIP-KAKA | B5: TEMP | C5: =DATE(2022, 10, 28) -> 44862 | D5: 2500 | J5: CURRENT AVAILABLE BALANCE: | K5: =K4 - (D34) -> 2917
A6: Electricity | B6: FAMILY | C6: =DATE(2022, 10, 28) -> 44862 | D6: 5186
A7: MAA (UCO) | B7: EMI | C7: =DATE(2022, 10, 28) -> 44862 | D7: 500
A8: Jogodhatri Pujo | B8: PUJO | C8: =DATE(2022, 10, 28) -> 44862 | D8: 12000 | E8: Transfered to Joint A/C
A9: UTI-SIP | B9: SAVINGS | C9: =DATE(2022, 10, 28) -> 44862 | D9: 2000
A10: Arghya (Scooty) | B10: EMI | C10: =DATE(2022, 10, 28) -> 44862 | D10: 2350 | J10: EXPECTED AVAILABLE BALANCE: | K10: =K5 - D68 + (D52 + D53 + D5) -> 5417
A11: Flat rent | B11: BANGALORE | C11: =DATE(2022, 10, 28) -> 44862 | D11: 7500
A12: Arghya (EMI Chair) | B12: EMI | C12: =DATE(2022, 10, 28) -> 44862 | D12: 1925
A13: FlipKart Paylater | B13: PURCHASE | C13: =DATE(2022, 10, 28) -> 44862 | D13: 1799
A14: MAA | B14: EMI | C14: =DATE(2022, 10, 28) -> 44862 | D14: 500 | J14: Pujo amount | L14: =D8 + OCT!K14 -> 25000
A15: Pujo Shopping | B15: FAMILY | C15: =DATE(2022, 10, 28) -> 44862 | D15: 5000
A16: Puchu Birthday | B16: SOCIAL | C16: =DATE(2022, 10, 29) -> 44863 | D16: 700 | J16: JOGODHATRI PUJO EXPENSES
A17: Cash | B17: PERSONAL | C17: =DATE(2022, 10, 29) -> 44863 | D17: 3350 | J17: Sajh advance | K17: =DATE(2022, 10, 6) -> 44840 | L17: 2001
A18: MAA | B18: EMI | C18: INSTANT | D18: 12000 | J18: Electrical expenses | L18: 2550
A19: Cook | B19: FAMILY | C19: INSTANT | D19: 1000 | J19: Sajh advance (Chota) | L19: 2500
A20: Flat electricity | B20: BANGALORE | D20: 300 | J20: Thakur | L20: 15000
A21: MOBILE RECHARGE | B21: BILL | D21: =762 -> 762
A22: Mobile (EMI) | B22: EMI | C22: INSTANT | D22: 3278
A23: Puri Trip | B23: FAMILY | D23: 8000
A24: Jogodhatri Pujo | B24: FAMILY | D24: 4000
A25: Technical expenses | B25: TECHNICAL | D25: 2000
A26: WiFi | D26: 1357
A27: Misclenious | D27: 18497
J28: Total Pujo Expenses | L28: =SUM(L17:L26) -> 22051
J29: Remaining in Hand | L29: =L14-L28 -> 2949
C34: TOTAL EXPENSE | D34: =SUM(D3:D32) -> 133504
A37: PENDING
A38: PAYMENT REASON | B38: PAYMENT CATEGORY | D38: PAYMENT AMOUNT
C68: PENDING EXPENSE | D68: =SUM(D38:D66) -> 0
A73: Kaka | B73: PENDING | D73: 30000

Sheet DEC
A1: TOTAL EXPENSE LIST | J1: AVAILABLE FROM PREVIOUS MONTH: | K1: =NOV!K5 -> 2917
A2: PAYMENT REASON | B2: PAYMENT CATEGORY | C2: DATE | D2: PAYMENT AMOUNT | J2: INCOME IN CURRENT MONTH: | K2: 85098
A3: SAVINGS | B3: SAVINGS | C3: =DATE(2022, 11, 28) -> 44893 | D3: 10000
A4: Personal | B4: PERSONAL | C4: =DATE(2022, 11, 28) -> 44893 | D4: 5000 | J4: TOTAL AVAILABLE: | K4: =K1 + K2 + K3 -> 88015
A5: UTI-SIP | B5: SAVINGS | C5: =DATE(2022, 11, 28) -> 44893 | D5: 1000 | J5: CURRENT AVAILABLE BALANCE: | K5: =K4 - (D27) -> 7419
A6: Flat rent | B6: BANGALORE | C6: =DATE(2022, 11, 28) -> 44893 | D6: 7500
A7: Arghya (Scooty) | B7: EMI | C7: =DATE(2022, 11, 28) -> 44893 | D7: 2350
A8: Arghya (EMI Chair) | B8: EMI | C8: =DATE(2022, 11, 28) -> 44893 | D8: 1925
A9: SIP-KAKA | B9: TEMP | C9: =DATE(2022, 11, 28) -> 44893 | D9: 2500
A10: SIP | B10: SAVINGS | C10: =DATE(2022, 11, 28) -> 44893 | D10: 3000 | J10: EXPECTED AVAILABLE BALANCE: | K10: =K5 - D62 -> 7419
A11: Electricity | B11: FAMILY | C11: =DATE(2022, 11, 28) -> 44893 | D11: 5185
A12: MAA | B12: EMI | C12: =DATE(2022, 11, 28) -> 44893 | D12: 12000
A13: Cook | B13: FAMILY | C13: =DATE(2022, 11, 28) -> 44893 | D13: 1000
A14: Mobile (EMI) | B14: EMI | C14: =DATE(2022, 12, 1) -> 44896 | D14: 3278
A15: MAA (UCO) | B15: EMI | C15: =DATE(2022, 11, 28) -> 44893 | D15: 500
A16: Bangalore Train | B16: FAMILY | C16: =DATE(2022, 11, 28) -> 44893 | D16: =(3312+3313) -> 6625
A17: Office Expense | B17: SOCIAL | C17: =DATE(2022, 11, 30) -> 44895 | D17: 250
A18: USB-C to HDMI adapter | B18: PERSONAL | C18: =DATE(2022, 11, 29) -> 44894 | D18: 1380
A19: MOBILE RECHARGE | B19: BILL | D19: =762 -> 762
A20: Flat electricity | B20: BANGALORE | D20: 221
A21: Personal | B21: PERSONAL | D21: 15000
A22: Technical Expenses | B22: PERSONAL | D22: =(2000 - D18) -> 620
A23: MAA (UCO) | B23: EMI | C23: =DATE(2022, 12, 28) -> 44923 | D23: 500
C27: TOTAL EXPENSE | D27: =SUM(D3:D25) -> 80596
A31: PENDING
A32: PAYMENT REASON | B32: PAYMENT CATEGORY | D32: PAYMENT AMOUNT
C62: PENDING EXPENSE | D62: =SUM(D32:D60) -> 0
A67: Kaka | B67: PENDING | D67: 30000

Sheet JAN23
A1: TOTAL EXPENSE LIST | J1: AVAILABLE FROM PREVIOUS MONTH: | K1: 7300
A2: PAYMENT REASON | B2: PAYMENT CATEGORY | C2: DATE | D2: PAYMENT AMOUNT | J2: INCOME IN CURRENT MONTH: | K2: 73164
A3: Mobile (EMI) | B3: EMI | C3: =DATE(2023, 1, 1) -> 44927 | D3: 3278
A4: Electricity | B4: FAMILY | C4: =DATE(2022, 12, 30) -> 44925 | D4: 5186 | J4: TOTAL AVAILABLE: | K4: =K1 + K2 + K3 -> 80464
A5: Mobile Recharge (Rini) | B5: BILL | C5: =DATE(2022, 12, 31) -> 44926 | D5: 155 | J5: CURRENT AVAILABLE BALANCE: | K5: =K4 - (D27) -> 12248
A6: Flat rent | B6: BANGALORE | C6: =DATE(2023, 1, 1) -> 44927 | D6: 7500
A7: Arghya (Scooty) | B7: EMI | C7: =DATE(2023, 1, 1) -> 44927 | D7: 2350
A8: Arghya (EMI Chair) | B8: EMI | C8: =DATE(2023, 1, 1) -> 44927 | D8: 1925
A9: Personal | B9: PERSONAL | C9: =DATE(2022, 12, 31) -> 44926 | D9: 5000
A10: New Year Party | B10: SOCIAL | C10: =DATE(2022, 12, 31) -> 44926 | D10: 4885 | J10: EXPECTED AVAILABLE BALANCE: | K10: =K5 - D61 + D15 -> -1059
A11: UTI-SIP | B11: SAVINGS | C11: =DATE(2023, 1, 1) -> 44927 | D11: 2000
A12: SAVINGS | B12: SAVINGS | C12: =DATE(2023, 1, 1) -> 44927 | D12: 10000
A13: SIP | B13: SAVINGS | C13: =DATE(2023, 1, 1) -> 44927 | D13: 3000
A14: SIP-KAKA | B14: TEMP | C14: =DATE(2023, 1, 1) -> 44927 | D14: 2500
A15: New Year Party | B15: TEMP | C15: =DATE(2023, 1, 1) -> 44927 | D15: 4500
A16: Barasat Matrimony | B16: SUBSCRIPTION | C16: =DATE(2022, 12, 31) -> 44926 | D16: 551
A17: MAA | B17: EMI | D17: 12000
A18: Cook | B18: FAMILY | D18: 1000
A19: Fridge EMI | B19: EMI | D19: 2386
C27: TOTAL EXPENSE | D27: =SUM(D3:D25) -> 68216
A31: PENDING
A32: PAYMENT REASON | B32: PAYMENT CATEGORY | D32: PAYMENT AMOUNT
A33: Flat electricity | B33: BANGALORE | D33: 200
A34: MOBILE RECHARGE | B34: BILL | D34: =762-(155) -> 607
A37: Personal | B37: PERSONAL | D37: 15000
A38: Technical Expenses | B38: PERSONAL | D38: 2000
C61: PENDING EXPENSE | D61: =SUM(D33:D59) -> 17807
A66: Kaka | B66: PENDING | D66: 30000

Sheet FEB23
A1: TOTAL EXPENSE LIST | J1: AVAILABLE FROM PREVIOUS MONTH: | K1: 8579
A2: PAYMENT REASON | B2: PAYMENT CATEGORY | C2: DATE | D2: PAYMENT AMOUNT | J2: INCOME IN CURRENT MONTH: | K2: 78014
A3: Flat rent | B3: BANGALORE | C3: =DATE(2023, 2, 1) -> 44958 | D3: 7500
A4: Arghya (EMI Scooty) | B4: EMI | C4: =DATE(2023, 2, 1) -> 44958 | D4: 2350 | J4: TOTAL AVAILABLE: | K4: =K1 + K2 + K3 -> 86593
A5: Arghya (EMI Chair) | B5: EMI | C5: =DATE(2023, 2, 1) -> 44958 | D5: 1925 | J5: CURRENT AVAILABLE BALANCE: | K5: =K4 - (D27) -> 32759
A6: Arghya (EMI Friedge) | B6: EMI | C6: =DATE(2023, 2, 1) -> 44958 | D6: 1958
A7: Web Server | B7: TECHNICAL | C7: =DATE(2023, 2, 1) -> 44958 | D7: 1000
A8: Mobile (EMI) | B8: EMI | C8: =DATE(2023, 2, 1) -> 44958 | D8: 3278
A9: Electricity | B9: FAMILY | C9: =DATE(2023, 2, 1) -> 44958 | D9: 3078
A10: UTI-SIP | B10: SAVINGS | C10: =DATE(2023, 2, 1) -> 44958 | D10: 2000 | J10: EXPECTED AVAILABLE BALANCE: | K10: =K5 - D61 -> 26974
A11: MAA | B11: EMI | C11: =DATE(2023, 2, 1) -> 44958 | D11: 12000
A12: Cook | B12: FAMILY | C12: =DATE(2023, 2, 1) -> 44958 | D12: 1000
A13: SIP | B13: SAVINGS | C13: =DATE(2023, 2, 1) -> 44958 | D13: 3000
A14: SIP-KAKA | B14: TEMP | C14: =DATE(2023, 2, 1) -> 44958 | D14: 2500
A15: SAVINGS | B15: SAVINGS | C15: =DATE(2023, 2, 1) -> 44958 | D15: 10000
A16: WiFi | B16: PERSONAL | C16: =DATE(2023, 1, 28) -> 44954 | D16: 1180
A17: Mobile recharge | B17: BILL | C17: =DATE(2023, 2, 1) -> 44958 | D17: =155 * 3 -> 465
A18: UCO Bank | B18: EMI | C18: =DATE(2023, 1, 28) -> 44954 | D18: 500
A19: Water | B19: WATER | C19: =DATE(2023, 1, 29) -> 44955 | D19: 100
C27: TOTAL EXPENSE | D27: =SUM(D3:D25) -> 53834
A31: PENDING
A32: PAYMENT REASON | B32: PAYMENT CATEGORY | D32: PAYMENT AMOUNT
A33: Flat electricity | B33: BANGALORE | D33: 500
A35: MOBILE RECHARGE | B35: BILL | D35: =750 - D17 -> 285
A36: Personal | B36: PERSONAL | D36: 5000
H44: =SUM(D4:D42) -> 105953
H45: =D7 + SUM(D4:D6) -> 7233
C61: PENDING EXPENSE | D61: =SUM(D33:D59) -> 5785
A66: Kaka | B66: PENDING | D66: 30000

Sheet MAR23
A1: TOTAL EXPENSE LIST | J1: AVAILABLE FROM PREVIOUS MONTH: | K1: 15652
A2: PAYMENT REASON | B2: PAYMENT CATEGORY | C2: DATE | D2: PAYMENT AMOUNT | J2: INCOME IN CURRENT MONTH: | K2: 99389
A3: SIP | B3: SAVINGS | C3: =DATE(2023, 2, 28) -> 44985 | D3: 3000
A4: SIP-KAKA | B4: TEMP | C4: =DATE(2023, 2, 28) -> 44985 | D4: 2500 | J4: TOTAL AVAILABLE: | K4: =K1 + K2 + K3 -> 115041
A5: Personal | B5: PERSONAL | C5: =DATE(2023, 2, 28) -> 44985 | D5: 5000 | J5: CURRENT AVAILABLE BALANCE: | K5: =K4 - (D27) -> 18423
A6: SAVINGS | B6: SAVINGS | C6: =DATE(2023, 2, 28) -> 44985 | D6: 23000
A7: Electricity | B7: FAMILY | C7: =DATE(2023, 2, 28) -> 44985 | D7: 3077
A8: UTI-SIP | B8: SAVINGS | C8: =DATE(2023, 2, 28) -> 44985 | D8: 2000
A9: Flat rent | B9: BANGALORE | C9: =DATE(2023, 2, 28) -> 44985 | D9: 7500
A10: Arghya (EMI Chair) | B10: EMI | C10: =DATE(2023, 2, 28) -> 44985 | D10: 1925 | J10: EXPECTED AVAILABLE BALANCE: | K10: =K5 - D61 -> -96597
A11: Arghya (EMI Friedge) | B11: EMI | C11: =DATE(2023, 2, 28) -> 44985 | D11: 1958
A12: Web Server | B12: TECHNICAL | C12: =DATE(2023, 2, 28) -> 44985 | D12: 2000
A13: Mobile (EMI) | B13: EMI | C13: =DATE(2023, 2, 28) -> 44985 | D13: 3280
A14: Mobile Recharge(7908760756) | B14: BILL | C14: =DATE(2023, 2, 28) -> 44985 | D14: 155
A15: CC Bill (AXIS) | B15: CC | C15: =DATE(2023, 3, 1) -> 44986 | D15: 10933
A16: CC Bill (SBI) | B16: CC | C16: =DATE(2023, 3, 1) -> 44986 | D16: 11888
A17: MOBILE RECHARGE | B17: BILL | C17: online | D17: =700 - (155 * 1) -> 545
A18: MAA | B18: EMI | C18: cash | D18: 15000
A19: Cook | B19: FAMILY | C19: cash | D19: 1000
A20: UCO Bank | B20: EMI | C20: online | D20: 500
A21: WiFi | B21: PERSONAL | C21: online | D21: 1357
C27: TOTAL EXPENSE | D27: =SUM(D3:D25) -> 96618
A31: PENDING
A32: PAYMENT REASON | B32: PAYMENT CATEGORY | D32: PAYMENT AMOUNT
C61: PENDING EXPENSE | D61: =SUM(D17:D58) -> 115020
A66: Kaka | B66: PENDING | D66: 30000

Sheet APR23
A1: TOTAL EXPENSE LIST | K1: AVAILABLE FROM PREVIOUS MONTH: | L1: 889
A2: PAYMENT REASON | B2: PAYMENT CATEGORY | C2: DATE | D2: PAYMENT AMOUNT | K2: INCOME IN CURRENT MONTH: | L2: =(76709 + 1357 + 7000) -> 85066
A3: CC Bill (AXIS) | B3: CC | C3: =DATE(2023, 3, 30) -> 45015 | D3: 3115
A4: Electricity | B4: FAMILY | C4: =DATE(2023, 3, 30) -> 45015 | D4: 3077 | K4: TOTAL AVAILABLE: | L4: =L1 + L2 + L3 -> 85955
A5: Flat rent | B5: BANGALORE | C5: =DATE(2023, 3, 30) -> 45015 | D5: 7500 | K5: CURRENT AVAILABLE BALANCE: | L5: =L4 - (D27) -> 5696
A6: Arghya (EMI Friedge) | B6: EMI | C6: =DATE(2023, 3, 30) -> 45015 | D6: 1960
A7: SIP | B7: SAVINGS | C7: =DATE(2023, 3, 30) -> 45015 | D7: 3000
A8: Kaka | B8: Temp | D8: 0
A9: SAVINGS | B9: SAVINGS | C9: =DATE(2023, 3, 30) -> 45015 | D9: 15000
A10: UTI-SIP | B10: SAVINGS | C10: =DATE(2023, 3, 30) -> 45015 | D10: 2000 | K10: EXPECTED AVAILABLE BALANCE: | L10: =L5 - D61 -> 4151
A11: Personal | B11: PERSONAL | C11: =DATE(2023, 3, 30) -> 45015 | D11: 1500
A12: MAA | B12: EMI | C12: =DATE(2023, 4, 2) -> 45018 | D12: 12000
A13: Cook | B13: FAMILY | C13: =DATE(2023, 4, 2) -> 45018 | D13: 1000 | K13: Savings | L13: =(115000 - 75000) -> 40000
A14: UCO Bank | B14: EMI | C14: =DATE(2023, 4, 1) -> 45017 | D14: 500
A15: Mobile (EMI) | B15: EMI | C15: =DATE(2023, 4, 1) -> 45017 | D15: 3280
A16: Flight ticket EMI | B16: EMI | C16: =DATE(2023, 4, 1) -> 45017 | D16: 1265
A17: Doctor | B17: MEDICAL | C17: =DATE(2023, 4, 1) -> 45017 | D17: =(1000 + 1000 + 1000 + 1000 + 3500) -> 7500
A18: cash | B18: PERSONAL | C18: =DATE(2023, 4, 1) -> 45017 | D18: 1000
A19: WiFi | B19: PERSONAL | C19: =DATE(2023, 4, 9) -> 45025 | D19: 1357
A20: Mobile Recharge(8617414770) | B20: BILL | C20: =DATE(2023, 4, 10) -> 45026 | D20: 155
A21: marketting | B21: FAMILY | C21: =DATE(2023, 4, 13) -> 45029 | D21: 2000
A22: maa | D22: =(11000 + 1000) -> 12000
A23: Mislenious | D23: 50
A24: Cash | B24: PERSONAL | C24: =DATE(2023, 4, 2) -> 45018 | D24: 1000
C27: TOTAL EXPENSE | D27: =SUM(D3:D25) -> 80259
A31: PENDING
A32: PAYMENT REASON | B32: PAYMENT CATEGORY | D32: PAYMENT AMOUNT
A33: Personal | B33: PERSONAL | C33: online | D33: 1000
A34: MOBILE RECHARGE | B34: BILL | C34: online | D34: =(700 - D20) -> 545
C61: PENDING EXPENSE | D61: =SUM(D33:D58) -> 1545
A66: Kaka | B66: PENDING | D66: 30000

Sheet MAY23
A1: TOTAL EXPENSE LIST | K1: AVAILABLE FROM PREVIOUS MONTH: | L1: ='APR23'!L5 -> 5696
A2: PAYMENT REASON | B2: PAYMENT CATEGORY | C2: DATE | D2: PAYMENT AMOUNT | G2: Color Code | H2: Category | K2: INCOME IN CURRENT MONTH: | L2: =92401 + 1357 -> 93758
A3: MOBILE RECHARGE | B3: BILL | C3: =DATE(2023, 4, 27) -> 45043 | D3: 150 | H3: Bills
A4: CC Bill (AXIS) | B4: CC | C4: =DATE(2023, 4, 27) -> 45043 | D4: =(7018 + 242) -> 7260 | H4: Savings | K4: TOTAL AVAILABLE: | L4: =L1 + L2 -> 99454
A5: Electricity | B5: FAMILY | C5: =DATE(2023, 4, 27) -> 45043 | D5: 3909 | H5: Maa | K5: CURRENT AVAILABLE BALANCE: | L5: =L4 - D39 + D35 -> 12657.87
A6: SIP | B6: SAVINGS | C6: =DATE(2023, 4, 27) -> 45043 | D6: 3000 | H6: Personal
A7: SAVINGS | B7: SAVINGS | C7: =DATE(2023, 4, 27) -> 45043 | D7: 35000 | H7: TEMP
A8: UCO Bank | B8: EMI | C8: =DATE(2023, 4, 27) -> 45043 | D8: 500 | H8: UNPLANNED
A9: Flat rent | B9: BANGALORE | C9: =DATE(2023, 4, 29) -> 45045 | D9: 8500
A10: Arghya (EMI Friedge) | B10: EMI | C10: =DATE(2023, 4, 29) -> 45045 | D10: 1960 | K10: EXPECTED AVAILABLE BALANCE: | L10: =L5 - D51 + (SUMIFS(D3:D32, B3:B32, "=TEMP")) -> 9672.87
A11: UTI-SIP | B11: SAVINGS | C11: =DATE(2023, 4, 29) -> 45045 | D11: 2000
A12: Clz trip | B12: PERSONAL | C12: =DATE(2023, 5,1) -> 45047 | D12: 3000
A13: MAA | B13: EMI | C13: =DATE(2023, 5,2) -> 45048 | D13: 5000
A14: Cook | B14: FAMILY | C14: =DATE(2023, 5,2) -> 45048 | D14: 1000 | K14: SAVINGS | L14: =(40000 - 20000 + D7) -> 55000
A15: MAA | B15: EMI | C15: =DATE(2023, 5,2) -> 45048 | D15: 1000
A16: Mobile Recharge (7908760756) | B16: BILL | C16: =DATE(2023, 5,2) -> 45048 | D16: 155
A17: GCETTB medical donation | B17: SOCIAL | C17: =DATE(2023, 5,2) -> 45048 | D17: 1000
A18: Mobile (EMI) | B18: EMI | C18: =DATE(2023, 5,4) -> 45050 | D18: 3280
A19: Flight ticket [KAKA] (EMI) | B19: EMI | C19: =DATE(2023, 5,4) -> 45050 | D19: =1265+270 -> 1535
A20: Train Ticket | B20: PERSONAL | C20: =DATE(2023, 5,8) -> 45054 | D20: =(77.15 + 88.6) -> 165.75
A21: Cash | B21: PERSONAL | C21: =DATE(2023, 5,4) -> 45050 | D21: 2000
A22: Mobile recharge (baba jio) | B22: BILL | D22: 155
A23: WiFi | B23: PERSONAL | C23: =DATE(2023, 5,11) -> 45057 | D23: 1357
A24: PMJJBY RENEWAL | B24: MISLENIOUS | C24: =DATE(2023, 5,8) -> 45054 | D24: 436
A25: Train Ticket | C25: =DATE(2023, 5,8) -> 45054 | D25: 77
A26: Clz Fest Contribution | B26: SOCIAL | C26: =DATE(2023, 5,15) -> 45061 | D26: 1000
A27: Bangalore WiFi | B27: BILL | C27: =DATE(2023, 5,15) -> 45061 | D27: 228.38
A28: Mobile recharge (Maa airtel) | B28: BILL | C28: =DATE(2023, 5,15) -> 45061 | D28: 155
A29: Gas | B29: BANGALORE | C29: =DATE(2023, 5,23) -> 45069 | D29: 600
A30: Water | B30: BANGALORE | C30: =DATE(2023, 5,21) -> 45067 | D30: 100
A31: WiFi | B31: PERSONAL | C31: =DATE(2023, 5,21) -> 45067 | D31: 236
A32: FoodBook recharge | B32: PERSONAL | C32: =DATE(2023, 5,22) -> 45068 | D32: 500
A33: Mobile recharge (3) | B33: BILL | D33: =(155 * 3) -> 465
A34: PayTm | B34: PERSONAL | C34: =DATE(2023, 5,26) -> 45072 | D34: 2000
A35: Inverse payment | D35: 928
C39: TOTAL EXPENSE | D39: =SUM(D3:D34) -> 87724.13
A43: PENDING
A44: PAYMENT REASON | B44: PAYMENT CATEGORY | D44: PAYMENT AMOUNT
A45: MOBILE RECHARGE | B45: BILL | C45: online | D45: =(800 - (D3 + D16 + D22 + D28)) -> 185
E46: =SUM(D45) -> 185
A47: Personal | B47: PERSONAL | C47: hybrid | D47: =(8000 - (D21 + D29 + D30 + D32 + D34)) -> 2800 | E47: =D47 -> 2800
C51: PENDING EXPENSE | D51: =SUM(D45:D49) -> 2985
A54: Kaka | B54: PENDING | D54: 30000

Sheet JUN23
A1: TOTAL EXPENSE LIST | K1: AVAILABLE FROM PREVIOUS MONTH: | L1: ='MAY23'!L5 -> 12657.87
A2: PAYMENT REASON | B2: PAYMENT CATEGORY | C2: DATE | D2: PAYMENT AMOUNT | G2: Color Code | H2: Category | K2: INCOME IN CURRENT MONTH: | L2: 96120
A3: CC Bill (AXIS) | B3: CC | C3: =DATE(2023, 5, 30) -> 45076 | D3: =(7810 + 2693) -> 10503 | H3: Bills | K3: Interest | L3: 128
A4: Electricity | B4: FAMILY | C4: =DATE(2023, 5, 31) -> 45077 | D4: 3909 | H4: Savings | K4: TOTAL AVAILABLE: | L4: =L1 + L2 + L3 -> 108905.87
A5: Flat rent | B5: BANGALORE | C5: =DATE(2023, 5, 30) -> 45076 | D5: 8500 | H5: Maa | K5: CURRENT AVAILABLE BALANCE: | L5: =L4 - (D40) -> 8227.87
A6: Arghya (EMI Friedge) | B6: EMI | C6: =DATE(2023, 5, 30) -> 45076 | D6: 1960 | H6: Personal
A7: Flight ticket [KAKA] (EMI) | B7: EMI | C7: =DATE(2023, 6, 19) -> 45096 | D7: 1265 | H7: Temp
A8: SIP | B8: SAVINGS | C8: =DATE(2023, 5, 30) -> 45076 | D8: 3000
A9: UTI-SIP | B9: SAVINGS | C9: =DATE(2023, 5, 30) -> 45076 | D9: 2000
A10: Mobile recharge(Maa Jio) | B10: BILL | C10: =DATE(2023, 5, 30) -> 45076 | D10: 155 | K10: EXPECTED AVAILABLE BALANCE: | L10: =L5 - D64 + (SUMIFS(D3:D25, B3:B25, "=TEMP")) -> 4210.87
A11: Medical Support | B11: SAVINGS | C11: =DATE(2023, 5, 31) -> 45077 | D11: 2000
A12: SAVINGS | B12: SAVINGS | C12: =DATE(2023, 5, 31) -> 45077 | D12: 45000
A13: MAA | B13: EMI | C13: =DATE(2023, 5, 31) -> 45077 | D13: 10000
A14: Cook | B14: FAMILY | C14: =DATE(2023, 5, 31) -> 45077 | D14: 1000 | K14: SAVINGS | L14: =(40000 + D12) -> 85000
A15: UCO Bank | B15: EMI | C15: =DATE(2023, 5, 31) -> 45077 | D15: 500
A16: FoodBook recharge | B16: PERSONAL | C16: =DATE(2023, 6, 1) -> 45078 | D16: 1000
A17: paytm | B17: PERSONAL | C17: =DATE(2023, 6, 2) -> 45079 | D17: 2000
A18: Paytm PostPaid recharge | B18: BILL | C18: =DATE(2023, 6, 4) -> 45081 | D18: 840
A19: Paytm | B19: PERSONAL | C19: =DATE(2023, 6, 6) -> 45083 | D19: 1000
A20: Mobile recharge(Baba Jio) | B20: BILL | C20: =DATE(2023, 6, 5) -> 45082 | D20: 155
A21: WiFi | B21: BILL | C21: =DATE(2023, 6, 8) -> 45085 | D21: 1357
A22: Mobile recharge(Airtel) | B22: BILL | C22: =DATE(2023, 6, 14) -> 45091 | D22: 155
A23: Mobile recharge(Maa Airtel) | B23: BILL | C23: =DATE(2023, 6, 10) -> 45087 | D23: 155
A24: Water | B24: PERSONAL | C24: =DATE(2023, 6, 14) -> 45091 | D24: 100
A25: Grocery | B25: PERSONAL | C25: =DATE(2023, 6, 14) -> 45091 | D25: 843
A26: WiFi (Airtel) | B26: BILL | C26: =DATE(2023, 6, 18) -> 45095 | D26: 1088
A27: Mobile recharge(Jio) | B27: BILL | C27: =DATE(2023, 6, 14) -> 45091 | D27: 155
A28: Mobile recharge(Rini) | B28: BILL | C28: =DATE(2023, 6, 14) -> 45091 | D28: 155
A29: Electricity | B29: BILL | C29: =DATE(2023, 6, 19) -> 45096 | D29: 583
A30: Paytm | B30: PERSONAL | C30: =DATE(2023, 6, 27) -> 45104 | D30: 1300
C40: TOTAL EXPENSE | D40: =SUM(D3:D30) -> 100678
A46: PENDING
A47: PAYMENT REASON | B47: PAYMENT CATEGORY | D47: PAYMENT AMOUNT
E50: =SUM(D48:D50) -> 0
A52: SIP | B52: SAVINGS | C52: online | D52: 3000
A59: Personal | B59: PERSONAL | C59: online | D59: =(8000 - (D16 + D17 + D18 + D19 + D25 + D30)) -> 1017 | E59: =D59 -> 1017
C64: PENDING EXPENSE | D64: =SUM(D48:D62) -> 4017
A66: Kaka | B66: PENDING | D66: 30000

Sheet JUL23
A1: TOTAL EXPENSE LIST | K1: AVAILABLE FROM PREVIOUS MONTH: | L1: ='JUN23'!L5 -> 8227.87
A2: PAYMENT REASON | B2: PAYMENT CATEGORY | C2: DATE | D2: PAYMENT AMOUNT | G2: Color Code | H2: Category | K2: INCOME IN CURRENT MONTH: | L2: 92401
A3: Mobile recharge(Maa Jio) | B3: BILL | C3: =DATE(2023, 6, 30) -> 45107 | D3: 155 | E3: 1 | H3: Bills
A4: CC Bill (AXIS) | B4: CC | C4: =DATE(2023, 6, 30) -> 45107 | D4: 6662 | E4: 1 | H4: Savings | K4: TOTAL AVAILABLE: | L4: =L1 + L2 -> 100628.87
A5: CC Bill (SBI) | B5: CC | C5: =DATE(2023, 6, 30) -> 45107 | D5: 8763 | E5: 1 | H5: Maa | K5: CURRENT AVAILABLE BALANCE: | L5: =L4 - (D32) -> 11728.87
A6: Electricity | B6: FAMILY | C6: =DATE(2023, 6, 30) -> 45107 | D6: 3909 | E6: 1 | H6: Personal
A7: Sagnik Marriage | B7: SOCIAL | C7: =DATE(2023, 6, 29) -> 45106 | D7: 1500 | E7: 1 | H7: Temp
A8: Sagnik Marriage | B8: TEMP | C8: =DATE(2023, 6, 29) -> 45106 | D8: =(3698 - 1500) -> 2198 | E8: 2
A9: Home Work | B9: SAVINGS | C9: online | D9: 40000 | E9: 1
A10: SIP | B10: SAVINGS | C10: online | D10: 3000 | E10: 1 | K10: EXPECTED AVAILABLE BALANCE: | L10: =L5 - D61 + (SUMIFS(D3:D30, B3:B30, "=TEMP")) -> -237.13
A11: UTI-SIP | B11: SAVINGS | C11: online | D11: 2000 | E11: 1
A12: MAA | B12: EMI | C12: cash | D12: 9000
A13: Cook | B13: FAMILY | C13: cash | D13: 1000
A14: Prem Birthday | B14: SOCIAL | D14: 500 | E14: 1 | K14: TEMP | L14: =(SUMIFS(D3:D30, B3:B30, "=TEMP")) -> 11237
A15: Prem Birthday | B15: TEMP | D15: 5110 | E15: 2
A16: Mobile recharge(Baba Jio) | B16: BILL | D16: 155 | E16: 1
A17: Water | B17: PERSONAL | D17: =100 + 100 -> 200
A18: SpicyTable | B18: PERSONAL | D18: 330
A19: SpicyTable (Rishi) | B19: TEMP | D19: 520
A20: SpicyTable (Arghya) | B20: TEMP | D20: 330
A21: KAKA SIP | B21: TEMP | D21: 2500 | E21: 2
A22: Chicken | B22: PERSONAL | D22: 140
A23: Arghya TEMP | B23: TEMP | D23: =140+90+349 -> 579
A24: Dinner 1st Jul | B24: PERSONAL | D24: 349
C32: TOTAL EXPENSE | D32: =SUM(D3:D30) -> 88900
A35: PENDING
A36: PAYMENT REASON | B36: PAYMENT CATEGORY | D36: PAYMENT AMOUNT
A37: MOBILE RECHARGE | B37: BILL | C37: online | D37: =(800 - (D3 + D16)) -> 490
A38: Flight ticket [KAKA] (EMI) | B38: EMI | C38: online | D38: 1265
A39: WiFi | B39: PERSONAL | C39: online | D39: =(1357 + 1150) -> 2507
A43: Flat rent | B43: BANGALORE | C43: online | D43: 8500
A44: Arghya (EMI Friedge) | B44: EMI | C44: online | D44: 1960 | E44: =SUM(D37:D44) -> 14722
A46: BackUp | B46: SAVINGS | C46: online | D46: 2000
E49: =SUM(D10:D11) -> 5000
A53: UCO Bank | B53: EMI | C53: online | D53: 500 | E53: =SUM(D12:D53) -> 126835
A55: Personal | B55: PERSONAL | C55: online | D55: =7000 - (SUMIFS(D3:D25, B3:B25, "=PERSONAL")) -> 5981
E56: =D55 + D7 -> 7481
C61: PENDING EXPENSE | D61: =SUM(D37:D59) -> 23203
A66: Kaka | B66: PENDING | D66: 30000

Sheet AUG23
A1: TOTAL EXPENSE LIST | K1: AVAILABLE FROM PREVIOUS MONTH: | L1: 3313
A2: PAYMENT REASON | B2: PAYMENT CATEGORY | C2: DATE | D2: PAYMENT AMOUNT | G2: Color Code | H2: Category | K2: INCOME IN CURRENT MONTH: | L2: 196555
H3: Bills
A4: WiFi recharge (Bangalore) | B4: BILL | C4: =DATE(2023, 7, 29) -> 45136 | D4: 1179 | H4: Savings | K4: TOTAL AVAILABLE: | L4: =L1 + L2 -> 199868
A5: Flat rent | B5: BANGALORE | C5: =DATE(2023, 7, 29) -> 45136 | D5: 8500 | H5: Maa | K5: CURRENT AVAILABLE BALANCE: | L5: =L4 - (D42) -> 16904
A6: Arghya (EMI Friedge) | B6: EMI | C6: =DATE(2023, 7, 29) -> 45136 | D6: 1960 | H6: Personal
A7: T-Shirt | B7: PERSONAL | C7: =DATE(2023, 7, 28) -> 45135 | D7: 1000 | H7: Temp
A8: Food | B8: PERSONAL | D8: =(517 + 208 + 134 + 212) -> 1071
A9: Water | B9: BILL | D9: =(100+100) -> 200 | S9: EXPECTED AVAILABLE BALANCE: | T9: =L5 - D65 + (SUMIFS(D5:D25, B5:B25, "=TEMP")) -> 13124
A11: Grocerry | C11: =DATE(2023, 7, 28) -> 45135 | D11: 356
A12: Saving | C12: =DATE(2023, 7, 30) -> 45137 | D12: 2300
A13: ITR Payment | C13: =DATE(2023, 7, 30) -> 45137 | D13: 390
A14: CC Bill (AXIS) | B14: CC | C14: =DATE(2023, 7, 30) -> 45137 | D14: 2649 | K14: SAVINGS | L14: =(40000 + D29) -> 160000
A15: CC Bill (RBL) | B15: TEMP | C15: =DATE(2023, 7, 30) -> 45137 | D15: 3315
A16: Ice-Cream | B16: PERSONAL | C16: =DATE(2023, 7, 31) -> 45138 | D16: 676
A17: Flight ticket [KAKA] (EMI) | B17: EMI | C17: =DATE(2023, 7, 31) -> 45138 | D17: 1265
A18: SIP | B18: SAVINGS | C18: =DATE(2023, 7, 31) -> 45138 | D18: 3000
A19: Personal | B19: PERSONAL | C19: =DATE(2023, 7, 31) -> 45138 | D19: 5000
A20: ITR payment | B20: BILL | C20: =DATE(2023, 7, 31) -> 45138 | D20: 1500
A21: UCO Bank | B21: EMI | C21: =DATE(2023, 7, 31) -> 45138 | D21: 500
A22: MAA | B22: EMI | C22: =DATE(2023, 8, 2) -> 45140 | D22: 12000
A23: Cook | B23: FAMILY | C23: =DATE(2023, 8, 2) -> 45140 | D23: 1000
A24: Electricity | B24: FAMILY | C24: =DATE(2023, 8, 2) -> 45140 | D24: 5571
A25: UTI-SIP | B25: SAVINGS | C25: =DATE(2023, 8, 2) -> 45140 | D25: 2000
A26: Mobile recharge | B26: BILL | C26: =DATE(2023, 7, 31) -> 45138 | D26: =(155+155+155) -> 465
A27: Paytm PostPaid | B27: BILL | C27: =DATE(2023, 8, 2) -> 45140 | D27: 3067
A28: Donation | B28: SOCIAL | C28: =DATE(2023, 8, 3) -> 45141 | D28: 4000
A29: Barir Kaj | B29: FAMILY | C29: =DATE(2023, 8, 4) -> 45142 | D29: 120000
C42: TOTAL EXPENSE | D42: =SUM(D3:D40) -> 182964
A46: PENDING
A47: PAYMENT REASON | B47: PAYMENT CATEGORY | D47: PAYMENT AMOUNT
A48: MOBILE RECHARGE | B48: BILL | C48: online | D48: =(800 - (D26)) -> 335
A50: WiFi | B50: PERSONAL | C50: online | D50: =(1357 + 1150) -> 2507 | E50: =SUM(D48:D50) -> 2842
E52: =D29 -> 120000
A54: Personal | B54: PERSONAL | C54: online | D54: =12000 - (D7 + D8 + D19 + D16) -> 4253 | E54: =D54 -> 4253
C65: PENDING EXPENSE | D65: =SUM(D48:D62) -> 7095
A88: Kaka | B88: PENDING | D88: 30000

Sheet SEP23
A1: TOTAL EXPENSE LIST | K1: AVAILABLE FROM PREVIOUS MONTH: | L1: 1130
A2: PAYMENT REASON | B2: PAYMENT CATEGORY | C2: DATE | D2: PAYMENT AMOUNT | G2: Color Code | H2: Category | K2: INCOME IN CURRENT MONTH: | L2: =94405+1178 -> 95583
A3: CC Bill (AXIS) | B3: CC | C3: Online | D3: 6472 | H3: Bills & EMI
A4: Water | C4: Online | D4: =100+100+100 -> 300 | H4: Savings | K4: TOTAL AVAILABLE: | L4: =L1 + L2 -> 96713
A5: Personal | B5: PERSONAL | C5: Online | D5: 2000 | H5: Maa | K5: CURRENT AVAILABLE BALANCE: | L5: =L4 - (D42) -> 35452
A6: CC Bill (SBI) | B6: CC | C6: Online | D6: 3657 | H6: Personal | K6: EXPECTED AVAILABLE BALANCE: | L6: =L5 - D75 + (SUMIFS(D7:D59, B7:B59, "=TEMP")) -> 24072
A7: SIP Temp | B7: TEMP | C7: Online | D7: 2500 | H7: Temp
A8: CC Bill (RBL) | B8: TEMP | C8: Online | D8: 2919
A9: SIP | B9: SAVINGS | C9: Online | D9: 3000
A10: Electricity | B10: BILL | C10: Online | D10: 5572
A11: Arghya (EMI Friedge) | B11: EMI | C11: Online | D11: 1960
A12: Flat rent | B12: BANGALORE | C12: Online | D12: 8500
A13: FlipKart Postpaid Payment | D13: 2844
A14: Mobile recharge (BABA Jio) | D14: 155
A15: Movie | D15: 715
A16: UTI-SIP | B16: SAVINGS | C16: Online | D16: 2000
A17: MAA | B17: EMI | C17: Online | D17: 11000
A18: Cook | B18: FAMILY | C18: Online | D18: 1000
A19: Paytm PostPaid | B19: CC | C19: Online | D19: 4000
A20: WiFi | B20: BILL | C20: Online | D20: 1357
A21: UCO Bank | B21: EMI | C21: Online | D21: 500
A22: Jio recharge | D22: 310
A23: FoodBook | B23: PERSONAL | D23: 500
C42: TOTAL EXPENSE | D42: =SUM(D3:D40) -> 61261
A46: PENDING
A47: PAYMENT REASON | B47: PAYMENT CATEGORY | D47: PAYMENT AMOUNT
A48: MOBILE RECHARGE | B48: BILL | C48: Online | D48: 800
A49: Flight ticket [KAKA] (EMI) | B49: EMI | C49: Online | D49: 1265
A50: WiFi | B50: BILL | C50: Online | D50: =(1179) -> 1179
A57: Bari EMI | B57: EMI | C57: Online | D57: 5555
E58: =SUM(D48:D57) - (D8 + D7) -> 3380
A59: Personal | B59: PERSONAL | C59: Online | D59: =(10000 - (D5)) -> 8000 | E59: =D59 -> 8000
E62: =SUM(D21) -> 500
C75: PENDING EXPENSE | D75: =SUM(D48:D72) -> 16799
A88: Kaka | B88: PENDING | D88: 30000

Sheet OCT23
A1: TOTAL EXPENSE LIST | K1: AVAILABLE FROM PREVIOUS MONTH: | L1: 1130
A2: PAYMENT REASON | B2: PAYMENT CATEGORY | C2: DATE | D2: PAYMENT AMOUNT | G2: Color Code | H2: Category | K2: INCOME IN CURRENT MONTH: | L2: =94405+1178 -> 95583
A3: CC Bill (AXIS) | B3: CC | C3: Online | D3: 6472 | H3: Bills & EMI
A4: Water | C4: Online | D4: =100+100+100 -> 300 | H4: Savings | K4: TOTAL AVAILABLE: | L4: =L1 + L2 -> 96713
A5: Personal | B5: PERSONAL | C5: Online | D5: 2000 | H5: Maa | K5: CURRENT AVAILABLE BALANCE: | L5: =L4 - (D42) -> 35452
A6: CC Bill (SBI) | B6: CC | C6: Online | D6: 3657 | H6: Personal | K6: EXPECTED AVAILABLE BALANCE: | L6: =L5 - D75 + (SUMIFS(D7:D59, B7:B59, "=TEMP")) -> 24072
A7: SIP Temp | B7: TEMP | C7: Online | D7: 2500 | H7: Temp
A8: CC Bill (RBL) | B8: TEMP | C8: Online | D8: 2919
A9: SIP | B9: SAVINGS | C9: Online | D9: 3000
A10: Electricity | B10: BILL | C10: Online | D10: 5572
A11: Arghya (EMI Friedge) | B11: EMI | C11: Online | D11: 1960
A12: Flat rent | B12: BANGALORE | C12: Online | D12: 8500
A13: FlipKart Postpaid Payment | D13: 2844
A14: Mobile recharge (BABA Jio) | D14: 155
A15: Movie | D15: 715
A16: UTI-SIP | B16: SAVINGS | C16: Online | D16: 2000
A17: MAA | B17: EMI | C17: Online | D17: 11000
A18: Cook | B18: FAMILY | C18: Online | D18: 1000
A19: Paytm PostPaid | B19: CC | C19: Online | D19: 4000
A20: WiFi | B20: BILL | C20: Online | D20: 1357
A21: UCO Bank | B21: EMI | C21: Online | D21: 500
A22: Jio recharge | D22: 310
A23: FoodBook | B23: PERSONAL | D23: 500
C42: TOTAL EXPENSE | D42: =SUM(D3:D40) -> 61261
A46: PENDING
A47: PAYMENT REASON | B47: PAYMENT CATEGORY | D47: PAYMENT AMOUNT
A48: MOBILE RECHARGE | B48: BILL | C48: Online | D48: 800
A49: Flight ticket [KAKA] (EMI) | B49: EMI | C49: Online | D49: 1265
A50: WiFi | B50: BILL | C50: Online | D50: =(1179) -> 1179
A57: Bari EMI | B57: EMI | C57: Online | D57: 5555
E58: =SUM(D48:D57) - (D8 + D7) -> 3380
A59: Personal | B59: PERSONAL | C59: Online | D59: =(10000 - (D5)) -> 8000 | E59: =D59 -> 8000
E62: =SUM(D21) -> 500
C75: PENDING EXPENSE | D75: =SUM(D48:D72) -> 16799
A88: Kaka | B88: PENDING | D88: 30000

Sheet DEC23
A1: TOTAL EXPENSE LIST | K1: AVAILABLE FROM PREVIOUS MONTH: | L1: 1818
A2: PAYMENT REASON | B2: PAYMENT CATEGORY | C2: DATE | D2: PAYMENT AMOUNT | G2: Color Code | H2: Category | K2: INCOME IN CURRENT MONTH: | L2: =99865+1357+1357 -> 102579
A3: CC Bill (AXIS) | B3: CC | C3: =DATE(2023, 11, 29) -> 45259 | D3: 5252 | H3: Bills & EMI
A4: CC Bill (SBI) | B4: CC | C4: =DATE(2023, 11, 29) -> 45259 | D4: 1836 | H4: Savings | K4: TOTAL AVAILABLE: | L4: =L1 + L2 -> 104397
A5: Arghya (EMI Friedge) | B5: EMI | C5: =DATE(2023, 11, 29) -> 45259 | D5: 1960 | H5: Maa | K5: CURRENT AVAILABLE BALANCE: | L5: =L4 - (D44) -> 4568
A6: Flat rent | B6: BANGALORE | C6: =DATE(2023, 11, 29) -> 45259 | D6: 8500 | H6: Personal | K6: EXPECTED AVAILABLE BALANCE: | L6: =L5 - D67 + (SUMIFS(D8:D62, B8:B62, "=TEMP")) -> 4178
A7: UCO Bank | B7: EMI | C7: =DATE(2023, 11, 29) -> 45259 | D7: 500 | H7: Temp
A8: Electricity | B8: BILL | C8: =DATE(2023, 11, 29) -> 45259 | D8: 3276 | H8: Family
A9: CC Bill (RBL) | B9: FAMILY | C9: =DATE(2023, 11, 29) -> 45259 | D9: 2899 | K9: Cash | L9: =(1400+500) -> 1900
A10: SIP Temp | B10: FAMILY | C10: =DATE(2023, 11, 29) -> 45259 | D10: 2500
A11: SIP | B11: SAVINGS | C11: =DATE(2023, 11, 29) -> 45259 | D11: 3000
A12: Bappa Kaka | B12: FAMILY | C12: =DATE(2023, 11, 29) -> 45259 | D12: 25000
A13: UTI-SIP | B13: SAVINGS | C13: =DATE(2023, 11, 29) -> 45259 | D13: 2000
A14: Mobile recharge(8653640704) | B14: BILL | C14: =DATE(2023, 11, 29) -> 45259 | D14: 155
A15: Cook | B15: FAMILY | C15: =DATE(2023, 11, 30) -> 45260 | D15: 4000
A16: Maa | B16: Maa | C16: =DATE(2023, 11, 30) -> 45260 | D16: 1000
A17: Kali Pujo | B17: FAMILY | C17: =DATE(2023, 11, 30) -> 45260 | D17: 6000
A18: Cash | B18: FAMILY | C18: =DATE(2023, 11, 30) -> 45260 | D18: 5000 | H18: 9169
A19: Air Bed | B19: FAMILY | C19: =DATE(2023, 11, 30) -> 45260 | D19: 2500
A20: Ladder | B20: FAMILY | C20: =DATE(2023, 11, 30) -> 45260 | D20: 2850
A21: Medicine (tab + molysheet) | B21: FAMILY | C21: =DATE(2023, 12, 3) -> 45263 | D21: =335+400+150 -> 885
A22: WiFi | B22: BILL | C22: =DATE(2023, 12, 5) -> 45265 | D22: =(1357) -> 1357
A23: Rent Mojo | B23: FAMILY | C23: =DATE(2023, 12, 7) -> 45267 | D23: =(514+463) - 489 -> 488
A24: Mobile recharge(8918405876) | B24: BILL | C24: =DATE(2023, 12, 7) -> 45267 | D24: 395
A25: Rice | B25: FAMILY | D25: 2000
A26: Cash | B26: FAMILY | D26: 3000
A27: Kali Pujo | B27: FAMILY | C27: Online | D27: 1500
A28: Office Marriage | B28: SOCIAL | C28: =DATE(2023, 12, 15) -> 45275 | D28: 1000
A29: Cab | B29: FAMILY | C29: =DATE(2023, 12, 10) -> 45270 | D29: =(230+332) -> 562
A30: Misc | D30: =(200 + 350+450+50+120+52+112)-914 -> 420
A31: Kitchen Goods | B31: FAMILY | D31: 1300
A32: Techno India | D32: 2700
A33: Reunion | B33: SOCIAL | C33: =DATE(2023, 12, 23) -> 45283 | D33: 4000
A34: IceCream | B34: PERSONAL | C34: =DATE(2023, 12, 23) -> 45283 | D34: 190
A35: Mobile recharge(8653640704) | B35: BILL | C35: =DATE(2023, 12, 7) -> 45267 | D35: 155
A36: Kitchen Self | B36: FAMILY | C36: =DATE(2023, 12, 22) -> 45282 | D36: 330
A37: Light Bulb | B37: FAMILY | C37: =DATE(2023, 12, 25) -> 45285 | D37: 140
A38: WiFi | B38: BILL | C38: =DATE(2023, 12, 26) -> 45286 | D38: =(1179) -> 1179
C44: TOTAL EXPENSE | D44: =SUM(D3:D40) -> 99829
A50: PENDING
A51: PAYMENT REASON | B51: PAYMENT CATEGORY | D51: PAYMENT AMOUNT
A52: MOBILE RECHARGE | B52: BILL | C52: Online | D52: =(700 - (D14 + D35)) -> 390
C67: PENDING EXPENSE | D67: =SUM(D52:D65) -> 390
A70: Kaka | B70: PENDING | D70: 30000
E73: =SUM(D70:D72) -> 30000

Sheet JAN-24
A1: TOTAL EXPENSE LIST | K1: AVAILABLE FROM PREVIOUS MONTH: | L1: ='DEC23'!L5 -> 4568
A2: PAYMENT REASON | B2: PAYMENT CATEGORY | C2: DATE | D2: PAYMENT AMOUNT | G2: Color Code | H2: Category | K2: INCOME IN CURRENT MONTH: | L2: 79971
A3: CC Bill (AXIS) | B3: CC | C3: Online | D3: 8663 | H3: Bills & EMI
A4: Electricity | B4: BILL | C4: Online | D4: 3276 | H4: Savings | K4: TOTAL AVAILABLE: | L4: =L1 + L2 -> 84539
A5: SIP Temp | B5: FAMILY | C5: Online | D5: 2500 | H5: Maa | K5: CURRENT AVAILABLE BALANCE: | L5: =L4 - (D32) -> 4200
A6: SIP | B6: SAVINGS | C6: Online | D6: 3000 | H6: Personal | K6: EXPECTED AVAILABLE BALANCE: | L6: =L5 - D68 + (SUMIFS(D14:D40, B14:B40, "=TEMP")) -> -2577
A7: MOBILE RECHARGE (Rini Jio) | B7: BILL | C7: Online | D7: 155 | H7: Temp
A8: Medicine | B8: FAMILY | C8: Online | D8: 175 | H8: Family
A9: Misc | B9: PERSONAL | C9: Online | D9: =(98 + 190 + 90 + 100 + 270) -> 748 | K9: Cash | L9: 2500
A10: Aya Registration | B10: FAMILY | C10: Online | D10: 250
A11: Ice cream | B11: PERSONAL | C11: Online | D11: 240
A12: CC Bill (SBI) | B12: CC | C12: Online | D12: 7740
A13: Interest received | B13: INCOME | C13: Online | D13: -11
A14: UTI-SIP | B14: SAVINGS | C14: Online | D14: 2000
A15: Flat rent | B15: BANGALORE | C15: Online | D15: 8500
A16: UCO Bank | B16: EMI | C16: Online | D16: 500
A17: CC Bill (RBL) | B17: FAMILY | C17: Online | D17: 2892
A18: Cook | B18: FAMILY | C18: Cash | D18: 4000
A19: MOBILE RECHARGE (Maa Airtel) | B19: BILL | C19: Online | D19: 155
A20: CC Bill (SBI) [Repeat] | B20: CC | C20: Online | D20: 7740
A21: WiFi | B21: BILL | C21: Online | D21: =(1357) -> 1357
A22: MOBILE RECHARGE (Rini Airtel) | B22: BILL | C22: Online | D22: 155
A23: PulseOxymeter + Oxygen | B23: FAMILY | C23: Online | D23: 1330
A24: Cash widrawl | B24: PERSONAL | C24: Cash | D24: 3300
A25: Train ticket | B25: PERSONAL | C25: Online | D25: 77
A26: MOBILE RECHARGE (Maa Airtel) | B26: BILL | C26: Online | D26: 155
A27: Rni mess charge | B27: FAMILY | C27: Online | D27: 5800
A28: Babu Kaka | B28: FAMILY | C28: Online | D28: 10000
A29: Others | D29: =(4285 + 1357) -> 5642
C32: TOTAL EXPENSE | D32: =SUM(D3:D30) -> 80339
A35: PENDING
A36: PAYMENT REASON | B36: PAYMENT CATEGORY | D36: PAYMENT AMOUNT
A37: MOBILE RECHARGE | B37: BILL | C37: Online | D37: =775 - (D7 + D19 + D22 + D26) -> 155
A39: Personal | B39: PERSONAL | C39: Online | D39: =4000-(D9 + D24) -> -48
A40: Damma | B40: FAMILY | C40: Cash | D40: =(8000 - D23) -> 6670
C68: PENDING EXPENSE | D68: =SUM(D37:D60) -> 6777
A71: Kaka | B71: PENDING | D71: 30000
A72: Bappa Kaka | B72: PENDING | D72: =(85000+9500)-('DEC23'!D12) -> 69500
A73: Babu Kaka | B73: PENDING | D73: 50000

Sheet FEB-24
A1: TOTAL EXPENSE LIST | K1: AVAILABLE FROM PREVIOUS MONTH: | L1: ='JAN-24'!L5 -> 4200
A2: PAYMENT REASON | B2: PAYMENT CATEGORY | C2: DATE | D2: PAYMENT AMOUNT | G2: Color Code | H2: Category | K2: INCOME IN CURRENT MONTH: | L2: =(92199+1357) -> 93556
A3: CC Bill (AXIS) | B3: CC | C3: Online | D3: 8303 | H3: Bills & EMI
A4: Round Fig Balance | B4: PERSONAL | C4: Online | D4: 200 | H4: Savings | K4: TOTAL AVAILABLE: | L4: =L1 + L2 -> 97756
A5: Electricity | B5: BILL | C5: Online | D5: 2873 | H5: Maa | K5: CURRENT AVAILABLE BALANCE: | L5: =L4 - (D32) -> 16477
A6: CC Bill (RBL) | B6: FAMILY | C6: Online | D6: 2884 | H6: Personal | K6: EXPECTED AVAILABLE BALANCE: | L6: =L5 - D68 + (SUMIFS(D14:D44, B14:B44, "=TEMP")) -> 10488
A7: UCO Bank | B7: EMI | C7: Online | D7: 500 | H7: Temp
A8: Flat rent | B8: BANGALORE | C8: Online | D8: 8500 | H8: Family
A9: SIP Temp | B9: FAMILY | C9: Online | D9: 2500 | K9: Cash | L9: 2500
A10: SIP | B10: SAVINGS | C10: Online | D10: 3000
A11: CC Bill (SBI) | B11: CC | C11: Online | D11: 571
A12: Cook | B12: FAMILY | C12: Cash | D12: 4000
A13: Maa | B13: Maa | C13: Cash | D13: 1000
A14: Cash | B14: FAMILY | C14: Cash | D14: 15000
A15: Prasenjit Kaka | C15: Online | D15: 15000
A16: WiFi | B16: BILL | C16: Online | D16: =(1357) -> 1357
A17: Dammar Kaj | B17: FAMILY | C17: Online | D17: =(1001 + 2240) -> 3241
A18: Mother's Hut | B18: FAMILY | C18: Online | D18: 620
A19: Table Cloth | D19: 730
A20: Mitali Studio | D20: =(500 + 1800) -> 2300
A21: DalPuri | D21: 200
A22: Bappa Kaka | D22: 8500
C32: TOTAL EXPENSE | D32: =SUM(D3:D30) -> 81279
A35: PENDING
A36: PAYMENT REASON | B36: PAYMENT CATEGORY | D36: PAYMENT AMOUNT
A37: MOBILE RECHARGE | B37: BILL | C37: Online | D37: 700
A38: Flight ticket [KAKA] (EMI) | B38: EMI | C38: Online | D38: =(1265 - 155) -> 1110
A39: WiFi | B39: BILL | C39: Online | D39: =(1179) -> 1179
A40: Personal | B40: PERSONAL | C40: Online | D40: 3000
C68: PENDING EXPENSE | D68: =SUM(D37:D60) -> 5989
A71: Kaka | B71: PENDING | D71: 30000
A72: Bappa Kaka | B72: PENDING | D72: =(85000+9500)-('DEC23'!D12) -> 69500
A73: Babu Kaka | B73: PENDING | D73: =(50000 - ('JAN-24'!D28)) -> 40000

Sheet MAR-24
A1: TOTAL EXPENSE LIST | K1: AVAILABLE FROM PREVIOUS MONTH: | L1: 5807
A2: PAYMENT REASON | B2: PAYMENT CATEGORY | C2: DATE | D2: PAYMENT AMOUNT | G2: Color Code | H2: Category | K2: INCOME IN CURRENT MONTH: | L2: =(131909 + 1357) -> 133266
A3: CC Bill (AXIS) | B3: CC | C3: Online | D3: 11713 | H3: Bills & EMI
A4: CC Bill (RBL) | B4: FAMILY | C4: Online | D4: 2877 | H4: Savings | K4: TOTAL AVAILABLE: | L4: =L1 + L2 -> 139073
A5: Invest | B5: SAVINGS | C5: Online | D5: 1500 | H5: Maa | K5: CURRENT AVAILABLE BALANCE: | L5: =L4 - (D47) -> 40787.5
A6: SIP Temp | B6: FAMILY | C6: Online | D6: 2500 | H6: Personal | K6: EXPECTED AVAILABLE BALANCE: | L6: =L5 - D68 + (SUMIFS(D14:D53, B14:B53, "=TEMP")) -> 21603.5
A7: SIP | B7: SAVINGS | C7: Online | D7: 5000 | H7: Temp
A8: Misc | B8: miscellaneous | C8: Online | D8: =(150 + 240 + 263.5 + 90 + 50 - 100) -> 693.5 | H8: Family
A9: UCO Bank | B9: EMI | C9: Online | D9: 500 | K9: Cash | L9: 2500
A10: Electricity | B10: BILL | C10: Online | D10: 2874
A11: Flat rent | B11: BANGALORE | C11: Online | D11: 8500
A12: Cook | B12: FAMILY | C12: Cash | D12: 4000
A13: Maa | B13: Maa | C13: Cash | D13: =(1000 + 2500) -> 3500 | L13: =SUM(9195+7069+4557)-3000-5000 -> 12821
A14: Train Ticket | B14: PERSONAL | C14: Online | D14: 78
A15: Mobile Recharge(8918405876) | B15: BILL | C15: Online | D15: 395 | L15: =SUM(L6+L13) -> 34424.5
A16: Mobile Recharge(KAKA) | B16: BILL | C16: Online | D16: =(179 + 29) -> 208
A17: Mobile Recharge(8653640704) | B17: BILL | C17: Online | D17: 155
A18: Medicine Shop | B18: FAMILY | C18: Online | D18: 770
A19: Temp SIP | B19: TEMP | C19: Online | D19: 5500
A20: CC Bill (SBI) | B20: CC | C20: Online | D20: 8344
A21: Kolkata trip | B21: FAMILY | C21: Online | D21: 2607
A22: Laptop | B22: FAMILY | C22: Online | D22: 13769
A23: Flight Ticket | B23: FAMILY | C23: Online | D23: 7000
A24: Mother's Hut | B24: FAMILY | C24: Online | D24: 945
A25: Office | B25: SOCIAL | C25: Online | D25: 500
A26: Wifi | B26: BILL | C26: Online | D26: 1357
A27: Bappa Kaka | B27: EMI | C27: Online | D27: 10000
A28: Cash | B28: PERSONAL | C28: Cash | D28: 2500
A29: Gift | B29: PERSONAL | C29: Online | D29: 500
C47: TOTAL EXPENSE | D47: =SUM(D3:D45) -> 98285.5
A50: PENDING
A51: PAYMENT REASON | B51: PAYMENT CATEGORY | D51: PAYMENT AMOUNT
A52: MOBILE RECHARGE | B52: BILL | C52: Online | D52: =(800 - SUM(D15)) -> 405
A53: WiFi | B53: BILL | C53: Online | D53: =(1179) -> 1179
A54: Personal | B54: PERSONAL | C54: Online | D54: =(10000-D28) -> 7500
A55: Family | B55: FAMILY | C55: Online | D55: 15000
A56: Sweets | B56: PERSONAL | C56: Online | D56: 600
C68: PENDING EXPENSE | D68: =SUM(D52:D60) -> 24684
A71: Kaka | B71: PENDING | D71: 30000
A72: Bappa Kaka | B72: PENDING | D72: =(85000+9500)-(('DEC23'!D12)+D27) -> 59500
A73: Babu Kaka | B73: PENDING | D73: =(50000 - ('JAN-24'!D28)) -> 40000

Sheet APR-24
A1: TOTAL EXPENSE LIST | K1: AVAILABLE FROM PREVIOUS MONTH: | L1: 5807
A2: PAYMENT REASON | B2: PAYMENT CATEGORY | C2: DATE | D2: PAYMENT AMOUNT | G2: Color Code | H2: Category | K2: INCOME IN CURRENT MONTH: | L2: =(85872) -> 85872
A3: CC Bill (AXIS) | B3: CC | C3: Online | D3: 5766 | H3: Bills & EMI
A4: CC Bill (SBI) | B4: CC | C4: Online | D4: 14590 | H4: Savings | K4: TOTAL AVAILABLE: | L4: =L1 + L2 -> 91679
A5: Laptop | B5: FAMILY | C5: Online | D5: 3150 | H5: Maa | K5: CURRENT AVAILABLE BALANCE: | L5: =L4 - (D32) -> 35107
A6: SIP Temp | B6: FAMILY | C6: Online | D6: 2500 | H6: Personal | K6: EXPECTED AVAILABLE BALANCE: | L6: =L5 - D68 + (SUMIFS(D14:D39, B14:B39, "=TEMP")) -> -11898
A7: SIP | B7: SAVINGS | C7: Online | D7: 5000 | H7: Temp
A8: UCO Bank | B8: EMI | C8: Online | D8: 500 | H8: Family
A9: Flat rent | B9: BANGALORE | C9: Online | D9: 8500 | K9: Cash | L9: 2500
A10: Electricity | B10: BILL | C10: Online | D10: 2926
A11: Flight ticket [KAKA] (EMI) | B11: EMI | C11: Online | D11: 948
A12: Marbel Palace | B12: FAMILY | C12: Online | D12: 5555
A13: Train(JamshedPur) | B13: FAMILY | C13: Online | D13: =(3356 + 2696+1085) -> 7137 | L13: =SUM(9195+7069+4557)-3000-5000 -> 12821
L15: =SUM(L6+L13) -> 923
C32: TOTAL EXPENSE | D32: =SUM(D3:D30) -> 56572
A35: PENDING
A36: PAYMENT REASON | B36: PAYMENT CATEGORY | D36: PAYMENT AMOUNT
A37: MOBILE RECHARGE | B37: BILL | C37: Online | D37: 700
A39: WiFi | B39: BILL | C39: Online | D39: =SUM(1179, 1357) -> 2536
A40: Personal | B40: PERSONAL | C40: Online | D40: 8000
A41: Family | B41: FAMILY | C41: Online | D41: 20000 | G41: =D12+D11 -> 6503
A42: CC Bill (RBL) | B42: FAMILY | C42: Online | D42: 2869
A43: Cook | B43: FAMILY | C43: Cash | D43: 4000
A44: Maa | B44: Maa | C44: Cash | D44: 2500
A46: Flight ticket [KAKA] (EMI) | D46: 6400
C68: PENDING EXPENSE | D68: =SUM(D37:D60) -> 47005
A71: Kaka | B71: PENDING | D71: 30000
A72: Bappa Kaka | B72: PENDING | D72: =(85000+9500)-(('DEC23'!D12) + ('MAR-24'!D27)) -> 59500
A73: Babu Kaka | B73: PENDING | D73: =(50000 - ('JAN-24'!D28)) -> 40000

Sheet MAY-24
A1: TOTAL EXPENSE LIST | K1: AVAILABLE FROM PREVIOUS MONTH: | L1: 7463
A2: PAYMENT REASON | B2: PAYMENT CATEGORY | C2: DATE | D2: PAYMENT AMOUNT | G2: Color Code | H2: Category | K2: INCOME IN CURRENT MONTH: | L2: =(104781) -> 104781
A3: Cook | B3: FAMILY | C3: Cash | D3: 4000 | H3: Bills & EMI
A4: Maa | B4: Maa | C4: Cash | D4: 3000 | H4: Savings | K4: TOTAL AVAILABLE: | L4: =L1 + L2 -> 112244
A5: CC Bill (AXIS) | B5: CC | C5: Online | D5: 8734 | H5: Maa | K5: CURRENT AVAILABLE BALANCE: | L5: =L4 - (D44) -> 14052
A6: CC Bill (SBI) | B6: CC | C6: Online | D6: 15414 | H6: Personal | K6: EXPECTED AVAILABLE BALANCE: | L6: =L5 - D56 + (SUMIFS(D3:D31, B3:B31, "=TEMP")) -> 3530
A7: Shirt | B7: PERSONAL | C7: Cash | D7: 1680 | H7: Temp
A8: Cash | B8: PERSONAL | C8: Cash | D8: 6320 | H8: Family
A9: Flat rent | B9: BANGALORE | C9: Online | D9: 8500 | K9: Cash | L9: 2500
A10: CC Bill (RBL) | B10: FAMILY | C10: Online | D10: 2861
A11: Electricity | B11: BILL | C11: Online | D11: =2661+904 -> 3565
A12: Hair Spa | B12: PERSONAL | C12: Online | D12: 1400
A13: Laptop | B13: FAMILY | C13: Online | D13: 3150
A14: SIP Temp | B14: FAMILY | C14: Online | D14: 2500
A15: SIP | B15: SAVINGS | C15: Online | D15: 5000 | G15: Banagalore Expenses
A16: Family | B16: FAMILY | C16: Online | D16: 15000 | G16: Water | H16: Online | I16: 100 | J16: =DATE(2024, 5, 18) -> 45430
A17: WiFi | B17: BILL | C17: Online | D17: 1357 | G17: Tea | H17: Online | I17: 20 | J17: =DATE(2024, 5, 18) -> 45430
A18: Rini(Jio) | B18: BILL | C18: Online | D18: =155+155 -> 310 | G18: Headphone | H18: Online | I18: 220 | J18: =DATE(2024, 5, 18) -> 45430
A19: miscellaneous | B19: miscellaneous | C19: Online | D19: =(230+50+5+108-6 + 40 + 29) + 905 -> 1361 | G19: Vegitables & More | H19: Online | I19: =SUM(309, 20,185,75) -> 589 | J19: =DATE(2024, 5, 19) -> 45431
A20: Camera + Mem Chip | B20: FAMILY | C20: Online | D20: 1880 | G20: Tea | H20: Online | I20: 22 | J20: =DATE(2024, 5, 19) -> 45431
A21: Maa Airtel | B21: BILL | C21: Online | D21: 155 | G21: Food Book | H21: Online | I21: 500 | J21: =DATE(2024, 5, 20) -> 45432
A22: UCO Bank | B22: EMI | C22: Online | D22: 500 | G22: Gas | H22: Online | I22: 400 | J22: =DATE(2024, 5, 20) -> 45432
A23: Train Ticket | B23: PERSONAL | C23: Online | D23: 77 | G23: Vegitables & More | H23: Online | I23: 131 | J23: =DATE(2024, 5, 20) -> 45432
A24: Card | B24: Marriage | C24: Online | D24: 500
A25: Lodge booking | B25: Marriage | C25: Online | D25: 5000
A26: SBI Life PMJJBY | B26: BILL | C26: Online | D26: 436
A27: Bangalore Journey | B27: PERSONAL | C27: Online | D27: =SUM(380, 40, 940) -> 1360
A28: Bangalore Expense | B28: PERSONAL | C28: Online | D28: =I32 -> 1982
A29: Rini Formfillup | B29: FAMILY | C29: Online | D29: 1200
A30: Himadri | B30: Temp | C30: Online | D30: 950
G32: Total | I32: =SUM(I16:I30) -> 1982
C44: TOTAL EXPENSE | D44: =SUM(D3:D42) -> 98192
A47: PENDING
A48: PAYMENT REASON | B48: PAYMENT CATEGORY | D48: PAYMENT AMOUNT
A49: MOBILE RECHARGE | B49: BILL | C49: Online | D49: =700-(D21+D18) -> 235
A50: Flight ticket [KAKA] (EMI) | B50: EMI | C50: Online | D50: 2400
A51: WiFi | B51: BILL | C51: Online | D51: =SUM(1179) -> 1179
A52: Personal | B52: PERSONAL | C52: Online | D52: =6000 - (D27+D28) -> 2658
A53: Family | B53: FAMILY | C53: Online | D53: 5000
C56: PENDING EXPENSE | D56: =SUM(D49:D55) -> 11472
A58: Kaka | B58: PENDING | D58: 30000
A59: Bappa Kaka | B59: PENDING | D59: =(85000+9500)-(('DEC23'!D12) + ('MAR-24'!D27)) -> 59500
A60: Babu Kaka | B60: PENDING | D60: =(50000 - ('JAN-24'!D28)) -> 40000
A61: Masi | B61: PENDING | D61: 50000
D63: =SUM(D58:D61) -> 179500

Sheet JUN-24
A1: TOTAL EXPENSE LIST | K1: AVAILABLE FROM PREVIOUS MONTH: | L1: 5828
A2: PAYMENT REASON | B2: PAYMENT CATEGORY | C2: DATE | D2: PAYMENT AMOUNT | G2: Color Code | H2: Category | K2: INCOME IN CURRENT MONTH: | L2: 196819
A3: CC Bill (AXIS) | B3: CC | C3: Online | D3: 9098 | H3: Bills & EMI
A4: CC Bill (SBI) | B4: CC | C4: Online | D4: 13555 | H4: Savings | K4: TOTAL AVAILABLE: | L4: =L1 + L2 -> 202647
A5: misc | B5: PERSONAL | C5: Online | D5: =SUM(41,30,65, 326, 45, 25, 50, 50, 53, 30, 100, 18, 185, 40,115,420, 75, 123, 1231, 20, 50, 56, 20, 25, 200, 47, 41, 10, 10, 20, 20, 75, 50, 30, 95, 23, 15, 155, 90, 23, 1500, 381, 20, 23, 20, 15, 50, 41, 15, 70, 23, 92) -> 6347 | H5: Maa | K5: CURRENT AVAILABLE BALANCE: | L5: =L4 - (D32) -> 14784
A6: FoodBook | B6: PERSONAL | C6: Online | D6: =(1000+1000) -> 2000 | H6: Personal | K6: EXPECTED AVAILABLE BALANCE: | L6: =L5 - D68 + (SUMIFS(D3:D30, B3:B30, "=TEMP")) -> -26
A7: UCO Bank | B7: EMI | C7: Online | D7: 500 | H7: Temp
A8: Electricity | B8: BILL | C8: Online | D8: =2659+535 -> 3194 | H8: Family
A9: Water | B9: PERSONAL | C9: Online | D9: =(100+100+100) -> 300 | K9: Cash | L9: 2500
A10: Laptop | B10: FAMILY | C10: Online | D10: 3150
A11: SIP Temp | B11: FAMILY | C11: Online | D11: 2500
A12: SIP | B12: SAVINGS | C12: Online | D12: 5000
A13: Family | B13: FAMILY | C13: Online | D13: 20050 | L13: =SUM(9195+7069+4557)-3000-5000 -> 12821
A14: Cook | B14: FAMILY | C14: Cash | D14: 4000
A15: Maa | B15: Maa | C15: Cash | D15: 5000 | L15: =SUM(L6+L13) -> 12795
A16: CC Bill (RBL) | B16: FAMILY | C16: Online | D16: 2869
A17: Gas | B17: PERSONAL | C17: Online | D17: 400
A18: WiFi | B18: BILL | C18: Online | D18: =SUM(1357) -> 1357
A19: Bappa Kaka | B19: PENDING | C19: Online | D19: =(85000+9500)-(('DEC23'!D12) + ('MAR-24'!D27) + 500) -> 59000
A20: Masi | B20: PENDING | C20: Online | D20: 30000
A21: Flat rent | B21: BANGALORE | C21: Online | D21: 10000
A22: Temp | B22: TEMP | C22: Online | D22: -11767
A23: Jamshedpore | B23: FAMILY | C23: Online | D23: 8000
A24: Share Investment | B24: SAVINGS | C24: Online | D24: =(5000+8000) -> 13000
A25: Mobile Recharge (Maa Jio) | B25: BILL | C25: Online | D25: 155
A26: Mobile Recharge (Rini Jio) | B26: BILL | C26: Online | D26: 155
C32: TOTAL EXPENSE | D32: =SUM(D3:D30) -> 187863
A35: PENDING
A36: PAYMENT REASON | B36: PAYMENT CATEGORY | D36: PAYMENT AMOUNT
A37: MOBILE RECHARGE | B37: BILL | C37: Online | D37: =(700 - (D25 + D26)) -> 390
A40: Personal | B40: PERSONAL | C40: Online | D40: =8000-SUM(D6, D5) -> -347
A42: Rini Ornaments | B42: FAMILY | C42: Online | D42: 3000
F46: =SUM(D10:D13) -> 30700
C68: PENDING EXPENSE | D68: =SUM(D37:D65) -> 3043
A71: Kaka | B71: PENDING | D71: =30000+16000 -> 46000
A72: Masi | B72: PENDING | D72: 20000
A73: Babu Kaka | B73: PENDING | D73: =(50000 - ('JAN-24'!D28)) -> 40000

Sheet JUL-24
A1: TOTAL EXPENSE LIST | K1: AVAILABLE FROM PREVIOUS MONTH: | L1: =28415+1100 - (18057+1100) -> 10358
A2: PAYMENT REASON | B2: PAYMENT CATEGORY | C2: DATE | D2: PAYMENT AMOUNT | G2: Color Code | H2: Category | K2: INCOME IN CURRENT MONTH: | L2: =(104782+218) + 464 + 1357 -> 106821
A3: Bangalore expenses | B3: PERSONAL | C3: 26-06-2024 | D3: =K18 -> 5172 | H3: Bills & EMI
A4: Wifi | B4: BILL | C4: 27-06-2024 | D4: 1179 | H4: Savings | K4: TOTAL AVAILABLE: | L4: =L1 + L2 -> 117179
A5: CC Bill (AXIS) | B5: CC | C5: 27-06-2024 | D5: =11538+11767 -> 23305 | H5: Maa | K5: CURRENT AVAILABLE BALANCE: | L5: =L4 - (D32) -> 13329
A6: CC Bill (SBI) | B6: CC | C6: 27-06-2024 | D6: 11056 | H6: Personal | K6: EXPECTED AVAILABLE BALANCE: | L6: =L5 - D68 + (SUMIFS(D14:D37, B14:B37, "=TEMP")) -> 10145
A7: Electricity | B7: BILL | C7: 27-06-2024 | D7: =2659 -> 2659 | H7: Temp
A8: UCO Bank | B8: EMI | C8: 27-06-2024 | D8: 500 | H8: Family
A9: Laptop | B9: FAMILY | C9: 27-06-2024 | D9: 3150 | K9: Cash | L9: 2500
A10: SIP Temp | B10: FAMILY | C10: 27-06-2024 | D10: 2500
A11: SIP | B11: SAVINGS | C11: 27-06-2024 | D11: 5000
A12: CC Bill (RBL) | B12: FAMILY | C12: 30-06-2024 | D12: 3434
A13: Mobile Recharge(Airtel Mine) | B13: BILL | C13: 45329 | D13: 155 | G13: Bangalore Expenses | L13: =SUM(9195+7069+4557)-3000-5000 -> 12821
G14: Type | H14: Date | I14: Amount
G15: Food | I15: =(81+100+39 +126 + 95+120+30+280+30+20+110+120+300+252+73+60+50+113+100+115) -> 2214 | L15: =SUM(L6+L13) -> 22966
A16: Family | B16: FAMILY | C16: Online | D16: 20000 | G16: Rapido | I16: =(50 + 41 + 41+41+56+41+47+41+41+41+ 41+62+41+56+70+41+73+41+75) -> 940
A17: CC Bill (HDFC) | B17: CC | C17: Online | D17: 3367 | G17: Refreshment | I17: =(15+20+15+15+10+10+15+10+20+15+10+20+10+25) -> 210
A18: WiFi | B18: BILL | C18: Online | D18: =SUM(1357) -> 1357 | G18: FoodBook | I18: 1000 | J18: Total | K18: =SUM(I15:I32) -> 5172
A19: Flat rent | B19: BANGALORE | C19: Online | D19: 10000 | G19: Misc | I19: -230
A20: Savings | B20: SAVINGS | C20: Online | D20: 8250 | G20: Grocery | I20: =(328+20) -> 348
A21: Electricity | B21: BILL | C21: Online | D21: 648 | G21: Medicine | I21: 129
A22: Jio Cinema Subscription | B22: BILL | C22: 45511 | D22: 29 | G22: Fish | I22: 105
A23: Tax Filing payment | B23: BILL | C23: 45542 | D23: 1000 | G23: Water | I23: =(100+100) -> 200
A24: Maa Diet | B24: FAMILY | D24: 900 | G24: Electronics & goods | I24: =(230+150) -> 380
G25: Msc | I25: -124
A26: Mobile Recharge(Maa Jio) | B26: BILL | D26: 189
C32: TOTAL EXPENSE | D32: =SUM(D3:D30) -> 103850
A35: PENDING
A36: PAYMENT REASON | B36: PAYMENT CATEGORY | D36: PAYMENT AMOUNT
A37: MOBILE RECHARGE | B37: BILL | C37: Online | D37: =(700-(D13 + D26)) -> 356
A39: Personal | B39: PERSONAL | C39: Online | D39: =(8000 - D3) -> 2828
C68: PENDING EXPENSE | D68: =SUM(D37:D60) -> 3184
A71: Kaka | B71: PENDING | D71: =30000+16000 -> 46000
A72: Masi | B72: PENDING | D72: 20000
A73: Babu Kaka | B73: PENDING | D73: =(50000 - ('JAN-24'!D28)) -> 40000

Sheet AUG-24
A1: TOTAL EXPENSE LIST | K1: AVAILABLE FROM PREVIOUS MONTH: | L1: =1722+1275 -> 2997
A2: PAYMENT REASON | B2: PAYMENT CATEGORY | C2: DATE | D2: PAYMENT AMOUNT | G2: Color Code | H2: Category | K2: INCOME IN CURRENT MONTH: | L2: =(104782+1187) -> 105969
A3: Bangalore Expenses | B3: PERSONAL | C3: 29-07-2024 | D3: =K18 -> 4808 | H3: Bills & EMI
A4: KAKA Flight EMI | C4: 29-07-2025 | D4: 2460 | H4: Savings | K4: TOTAL AVAILABLE: | L4: =L1 + L2 -> 108966
A5: Family | B5: FAMILY | C5: 29-07-2026 | D5: 20000 | H5: Maa | K5: CURRENT AVAILABLE BALANCE: | L5: =L4 - (D32) -> 5105
A6: Rini watch | B6: FAMILY | C6: 29-07-2027 | D6: 500 | H6: Personal | K6: EXPECTED AVAILABLE BALANCE: | L6: =L5 - D68 + (SUMIFS(D14:D37, B14:B37, "=TEMP")) -> 15986
A7: Rini watch return | C7: 29-07-2028 | D7: 1040 | H7: Temp
A8: Laptop | B8: FAMILY | C8: 29-07-2029 | D8: 3150 | H8: Family
A9: SIP Temp | B9: FAMILY | C9: 29-07-2030 | D9: 2500 | K9: Cash | L9: 2500
A10: SIP | B10: SAVINGS | C10: 29-07-2031 | D10: 5000
A11: Electricity | B11: BILL | C11: 29-07-2032 | D11: =4055 -> 4055
A12: UCO Bank | B12: EMI | C12: 29-07-2033 | D12: 500
A13: CC Bill (AXIS) | B13: CC | C13: 27-06-2024 | D13: 10256 | G13: Bangalore Expenses | L13: =SUM(9195+7069+4557)-3000-5000 -> 12821
A14: Temp | B14: TEMP | C14: 27-06-2025 | D14: =19157-4384 -> 14773 | G14: Type | H14: Date | I14: Amount
A15: Cook | B15: FAMILY | C15: 27-06-2026 | D15: 4000 | G15: Food | I15: =(40+100+90+80) -> 310 | L15: =SUM(L6+L13) -> 28807
A16: Maa | B16: Maa | C16: 27-06-2027 | D16: 3000 | G16: Company Food | I16: =(168+139 + 97 + 68+168+139+112+112+10+73+136+168+100+136+129+119+139) -> 2013
A17: CC Bill (SBI) | B17: CC | C17: 27-06-2028 | D17: 8089 | G17: Rapido | I17: =150+60+80+60+50 -> 400
A18: CC Bill (RBL) | B18: FAMILY | C18: 30-06-2024 | D18: 2837 | G18: Refreshment | I18: =(15+15+10+15+40+10+15) -> 120 | J18: Total | K18: =SUM(I15:I32) -> 4808
A19: Wifi | B19: BILL | C19: 27-06-2024 | D19: =1357 -> 1357 | G19: FoodBook
A20: Flat rent | B20: BANGALORE | C20: Online | D20: 10000 | G20: Misc | I20: =(300+40+110+47) -> 497
A21: Electricity | B21: BILL | C21: Online | D21: 678 | G21: Grocery | I21: =406+210+206 -> 822
A22: CC Bill (HDFC) | B22: CC | C22: Online | D22: 4858 | G22: Medicine | I22: =10+86 -> 96
G23: Fish
G24: Water | I24: =100 -> 100
G25: Gas | I25: 450
C32: TOTAL EXPENSE | D32: =SUM(D3:D30) -> 103861
A35: PENDING
A36: PAYMENT REASON | B36: PAYMENT CATEGORY | D36: PAYMENT AMOUNT
A37: MOBILE RECHARGE | B37: BILL | C37: Online | D37: =(700) -> 700
A38: Personal | B38: PERSONAL | C38: Online | D38: =8000-D3 -> 3192
C68: PENDING EXPENSE | D68: =SUM(D37:D65) -> 3892
A71: Kaka | B71: PENDING | D71: =30000+16000 -> 46000
A72: Masi | B72: PENDING | D72: 20000
A73: Babu Kaka | B73: PENDING | D73: =(50000 - ('JAN-24'!D28)) -> 40000

Sheet SEP-24
A1: TOTAL EXPENSE LIST | K1: AVAILABLE FROM PREVIOUS MONTH: | L1: 0
A2: PAYMENT REASON | B2: PAYMENT CATEGORY | C2: DATE | D2: PAYMENT AMOUNT | G2: Color Code | H2: Category | K2: INCOME IN CURRENT MONTH: | L2: =(106042+5616) -> 111658
A3: CC Bill (SBI) | B3: CC | C3: Online | D3: 13109 | H3: Bills & EMI
A4: CC Bill (AXIS) | B4: CC | C4: Online | D4: 13030 | H4: Savings | K4: TOTAL AVAILABLE: | L4: =L1 + L2 -> 111658
A5: Wifi | B5: BILL | C5: Online | D5: =1357 -> 1357 | H5: Maa | K5: CURRENT AVAILABLE BALANCE: | L5: =L4 - (D32) -> -2115
A6: Electricity | B6: BILL | C6: Online | D6: =4055+768 -> 4823 | H6: Personal | K6: EXPECTED AVAILABLE BALANCE: | L6: =L5 - D68 + (SUMIFS(D14:D37, B14:B37, "=TEMP")) -> -8777
A7: Laptop | B7: CC | C7: Online | D7: 3150 | H7: Temp
A8: SIP Kaka | B8: FAMILY | C8: Online | D8: 2500 | H8: Family
A9: SIP | B9: SAVINGS | C9: Online | D9: 5000
A10: Family | B10: FAMILY | C10: Online | D10: 20540
A11: KAKA Flight EMI | B11: CC | C11: Online | D11: 2460
A12: Cook | B12: FAMILY | C12: Online | D12: 4000
A13: Maa | B13: Maa | C13: Online | D13: 4000 | G13: Bangalore Expenses
A14: CC Bill (RBL) | B14: CC | C14: Online | D14: 2837 | G14: Type | H14: Date | I14: Amount
A15: Bangalore Expense | B15: PERSONAL | C15: Online | D15: =I32 -> 2038 | G15: Food | L15: =SUM(L6+L13) -> -8777
A16: UCO Bank | B16: FAMILY | C16: Online | D16: 500 | G16: Company Food
A17: Misc | D17: 3520 | G17: Rapido
A18: Flat rent | B18: BANGALORE | C18: Online | D18: 20000 | G18: Refreshment
A19: CC Bill (HDFC) | B19: CC | C19: Online | D19: 5909 | G19: FoodBook
A20: Baba Award | D20: 5000 | G20: Misc
G21: Grocery
G22: Medicine
G23: Fish | I23: =1650+388 -> 2038
G24: Water
G25: Gas
C32: TOTAL EXPENSE | D32: =SUM(D3:D30) -> 113773 | G32: Total | I32: =SUM(I15:I30) -> 2038
A35: PENDING
A36: PAYMENT REASON | B36: PAYMENT CATEGORY | D36: PAYMENT AMOUNT
A37: MOBILE RECHARGE | B37: BILL | C37: Online | D37: =(700) -> 700
A38: Personal | B38: PERSONAL | C38: Online | D38: =8000-D15 -> 5962
C68: PENDING EXPENSE | D68: =SUM(D37:D65) -> 6662
A71: Kaka | B71: PENDING | D71: =30000+16000 -> 46000
A72: Masi | B72: PENDING | D72: 20000
A73: Babu Kaka | B73: PENDING | D73: =(50000 - ('JAN-24'!D28)) -> 40000

Sheet OCT-24
A1: TOTAL EXPENSE LIST | K1: AVAILABLE FROM PREVIOUS MONTH: | L1: =1954 -> 1954
A2: PAYMENT REASON | B2: PAYMENT CATEGORY | C2: DATE | D2: PAYMENT AMOUNT | G2: Color Code | H2: Category | K2: INCOME IN CURRENT MONTH: | L2: =(107708+128+1357) -> 109193
A3: Bangalore Expense | B3: PERSONAL | C3: Online | D3: =I32 -> 6341.5 | H3: Bills & EMI
A4: CC Bill (AXIS) | B4: CC | C4: Online | D4: 12223 | H4: Savings | K4: TOTAL AVAILABLE: | L4: =L1 + L2 -> 111147
A5: CC Bill (SBI) | B5: CC | C5: Online | D5: 4772 | H5: Maa | K5: CURRENT AVAILABLE BALANCE: | L5: =L4 - (D32) -> 7226.5
A6: CC Bill (RBL) | B6: CC | C6: Online | D6: 2818 | H6: Personal | K6: EXPECTED AVAILABLE BALANCE: | L6: =L5 - D68 + (SUMIFS(D16:D36, B16:B36, "=TEMP")) -> 1568
A7: Electricity | B7: BILL | C7: Online | D7: =4054 -> 4054 | H7: Temp
A8: Wifi | B8: BILL | C8: Online | D8: =1357+1179 -> 2536 | H8: Family
A9: Cook | B9: FAMILY | C9: Online | D9: 6000
A10: Maa | B10: Maa | C10: Online | D10: 4000
A11: KAKA Flight EMI | C11: Online | D11: =2460-2350 -> 110
A12: Family | B12: FAMILY | C12: Online | D12: 20000
A13: Laptop | B13: FAMILY | C13: Online | D13: 3150 | G13: Bangalore Expenses
A14: SIP Temp | B14: FAMILY | C14: Online | D14: 2500 | G14: Type | H14: Date | I14: Amount
A15: SIP | B15: SAVINGS | C15: Online | D15: 5000 | G15: Food | I15: =50+100+825+100+230 -> 1305 | L15: =SUM(L6+L13) -> 1568
A16: UCO Bank | B16: EMI | C16: Online | D16: 500 | G16: Company Food | I16: =112+146+57+50+90+89 -> 544
A17: Arghya | B17: PERSONAL | C17: Online | D17: 900 | G17: Rapido | I17: =41+88+41+41+41+200+220+108+105 -> 885
A18: Donation | B18: SOCIAL | C18: Online | D18: 1100 | G18: Refreshment | I18: =15+20+100+18 -> 153
A19: CC Bill (HDFC) | B19: CC | C19: Online | D19: 5172 | G19: FoodBook
A20: Flat rent | B20: BANGALORE | C20: Online | D20: 20000 | G20: Misc | I20: =231 -> 231
A21: Electricity | B21: BILL | C21: Online | D21: 715 | G21: Grocery | I21: =197+50+23 -> 270
A22: Jio Cinema | B22: BILL | C22: Online | D22: 29 | G22: Medicine
A23: Barir Kaj | B23: FAMILY | D23: 2000 | G23: Fish & Meat | I23: 1257.5
G24: Water | I24: =100+100 -> 200
G25: Gas | I25: 400
G26: Mobile Recharge | I26: =77+19 -> 96
G27: Airport taxi | I27: 1000
C32: TOTAL EXPENSE | D32: =SUM(D3:D30) -> 103920.5 | G32: Total | I32: =SUM(I15:I30) -> 6341.5
A35: PENDING
A36: PAYMENT REASON | B36: PAYMENT CATEGORY | D36: PAYMENT AMOUNT
A37: Personal | B37: PERSONAL | C37: Online | D37: =7000 - D3 -> 658.5
A38: Kaka Bari Paint | B38: FAMILY | C38: Online | D38: 5000
A39: Kaka Mobile EMI | B39: EMI | C39: Online
C68: PENDING EXPENSE | D68: =SUM(D37:D65) -> 5658.5
A71: Kaka | B71: PENDING | D71: =30000+16000 -> 46000
A72: Masi | B72: PENDING | D72: 20000
A73: Babu Kaka | B73: PENDING | D73: =(50000 - ('JAN-24'!D28)) -> 40000

Sheet NOV-24
A1: TOTAL EXPENSE LIST | K1: AVAILABLE FROM PREVIOUS MONTH: | L1: =2660+7226 -> 9886
A2: PAYMENT REASON | B2: PAYMENT CATEGORY | C2: DATE | D2: PAYMENT AMOUNT | G2: Color Code | H2: Category | K2: INCOME IN CURRENT MONTH: | L2: =(106869+1357) -> 108226
A3: Maa | B3: Maa | C3: Online | D3: =2700+5000 -> 7700 | H3: Bills & EMI
A4: Flat rent | B4: BANGALORE | C4: Online | D4: 20000 | H4: Savings | K4: TOTAL AVAILABLE: | L4: =L1 + L2 -> 118112
A5: CC Bill (AXIS) | B5: CC | C5: Online | D5: 10727 | H5: Maa | K5: CURRENT AVAILABLE BALANCE: | L5: =L4 - (D32) -> 6542
A6: CC Bill (SBI) | B6: CC | C6: Online | D6: 12214 | H6: Personal | K6: EXPECTED AVAILABLE BALANCE: | L6: =L5 - D68 + (SUMIFS(D14:D37, B14:B37, "=TEMP")) -> 5221
A7: CC Bill (RBL) | B7: CC | C7: Online | D7: 2798 | H7: Temp
A8: Electricity | B8: BILL | C8: Online | D8: =2509+500 -> 3009 | H8: Family
A9: Wifi | B9: BILL | C9: Online | D9: =1357+297 -> 1654
A10: Arghya | B10: BANGALORE | C10: Online | D10: 4000
A11: UCO Bank | B11: EMI | C11: Online | D11: 500
A12: KAKA Flight EMI | B12: EMI | C12: Online | D12: 2460
A13: Family | B13: FAMILY | C13: Online | D13: 20000 | G13: Personal Expenses
A14: Laptop | B14: FAMILY | C14: Online | D14: 3150 | G14: Type | H14: Date | I14: Amount
A15: SIP | B15: SAVINGS | C15: Online | D15: 5000 | G15: Food | I15: =210+220+440+1000+48+150+30+15 -> 2113 | L15: =SUM(L6+L13) -> 5221
A16: SIP Temp | B16: FAMILY | C16: Online | D16: 2500 | G16: Company Food
A17: Personal Expense | B17: PERSONAL | C17: Online | D17: =I32 -> 3679 | G17: Rapido
A18: Camera (adv) | B18: MARRIAGE | C18: Online | D18: 1000 | G18: Refreshment
A19: Card adv | B19: MARRIAGE | C19: Online | D19: 4500 | G19: FoodBook
A20: Cash | D20: =699+15 -> 714 | G20: Misc | I20: =80+981 -> 1061
A21: CC Bill (HDFC) | B21: CC | C21: Online | D21: 5936 | G21: Grocery
A22: Jio cinema | B22: BILL | C22: Online | D22: 29 | G22: Medicine
G23: Fish
G24: Water
G25: Gas
G26: Shoe | I26: 450
G27: Maa | I27: 55
C32: TOTAL EXPENSE | D32: =SUM(D3:D30) -> 111570 | G32: Total | I32: =SUM(I15:I30) -> 3679
A35: PENDING
A36: PAYMENT REASON | B36: PAYMENT CATEGORY | D36: PAYMENT AMOUNT
A37: MOBILE RECHARGE | B37: BILL | C37: Online
A38: Personal | B38: PERSONAL | C38: Online | D38: =5000-D17 -> 1321
I39: =D14+D15+D13+D12 -> 30610
C68: PENDING EXPENSE | D68: =SUM(D37:D65) -> 1321
A71: Kaka | B71: PENDING | D71: =30000+16000 -> 46000
A72: Masi | B72: PENDING | D72: 20000
A73: Babu Kaka | B73: PENDING | D73: =(50000 - ('JAN-24'!D28)) -> 40000

Sheet DEC-24
A1: TOTAL EXPENSE LIST | K1: AVAILABLE FROM PREVIOUS MONTH: | L1: =3938+1874 -> 5812
A2: PAYMENT REASON | B2: PAYMENT CATEGORY | C2: DATE | D2: PAYMENT AMOUNT | G2: Color Code | H2: Category | K2: INCOME IN CURRENT MONTH: | L2: =(107586) -> 107586
A3: CC Bill (AXIS) | B3: CC | C3: Online | D3: 12673 | H3: Bills & EMI
A4: CC Bill (SBI) | B4: CC | C4: Online | D4: 5695 | H4: Savings | K4: TOTAL AVAILABLE: | L4: =L1 + L2 -> 113398
A5: Electricity | B5: BILL | C5: Online | D5: =2509+240 -> 2749 | H5: Maa | K5: CURRENT AVAILABLE BALANCE: | L5: =L4 - (D32) -> 12730
A6: KAKA Flight EMI | C6: Online | D6: 2460 | H6: Personal | K6: EXPECTED AVAILABLE BALANCE: | L6: =L5 - D68 + (SUMIFS(D2:D30, B2:B30, "=TEMP")) -> 14930
A7: Family | B7: FAMILY | C7: Online | D7: 20000 | H7: Temp
A8: UCO Bank | B8: EMI | C8: Online | D8: 500 | H8: Family
A9: Cook | B9: FAMILY | C9: Online | D9: 4000
A10: Maa | B10: Maa | C10: Online | D10: 5000
A11: Personal Expenses | B11: PERSONAL | C11: Online | D11: =I32 -> 1877
A12: Wifi | B12: BILL | C12: Online | D12: 1357
A13: SIP Temp | B13: TEMP | C13: Online | D13: 2500 | G13: Personal Expenses
A14: SIP | B14: SAVINGS | C14: Online | D14: 5000 | G14: Type | H14: Date | I14: Amount
A15: CC Bill (RBL) | B15: CC | C15: Online | D15: 2795 | G15: Food | I15: 100
A16: CC Bill (HDFC) | B16: CC | C16: Online | D16: 1939 | G16: Company Food
A17: Band advance (marriage) | B17: FAMILY | C17: Online | D17: 2000 | G17: Rapido | I17: =41+55+213+211+880+125 -> 1525
A18: Flat rent | B18: BANGALORE | C18: Online | D18: 20000 | G18: Refreshment
A19: Masi | B19: FAMILY | C19: Online | D19: 6000 | G19: FoodBook
A20: Personal | B20: PERSONAL | C20: Online | D20: =6000 - D11 -> 4123 | G20: Misc | I20: =7 -> 7
G21: Grocery
G22: Medicine | I22: 245
G23: Fish
G24: Water
G25: Gas
C32: TOTAL EXPENSE | D32: =SUM(D3:D30) -> 100668 | G32: Total | I32: =SUM(I15:I30) -> 1877
A35: PENDING
A36: PAYMENT REASON | B36: PAYMENT CATEGORY | D36: PAYMENT AMOUNT
A37: MOBILE RECHARGE | B37: BILL | C37: Online | D37: 300
A40: Wifi | B40: BILL | C40: Online | D40: 0
C68: PENDING EXPENSE | D68: =SUM(D37:D65) -> 300
A71: Kaka | B71: PENDING | D71: =30000+16000 -> 46000
A72: Masi | B72: PENDING | D72: 20000
A73: Babu Kaka | B73: PENDING | D73: =(50000 - ('JAN-24'!D28)) -> 40000

Sheet JAN-25
K1: AVAILABLE FROM PREVIOUS MONTH: | L1: 1667
A2: PAYMENT REASON | B2: PAYMENT CATEGORY | C2: DATE | D2: PAYMENT AMOUNT | G2: Color Code | H2: Category | K2: INCOME IN CURRENT MONTH: | L2: 101562
A3: CC Bill (AXIS) | B3: CC | C3: Online | D3: 10390 | H3: Bills & EMI
A4: CC Bill (SBI) | B4: CC | C4: Online | D4: 5668 | H4: Savings | K4: TOTAL AVAILABLE: | L4: =L1 + L2 -> 103229
A5: Electricity | B5: BILL | C5: Online | D5: =2509 -> 2509 | H5: Maa | K5: CURRENT AVAILABLE BALANCE: | L5: =L4 - (D32) -> 5069.2
A6: Wifi | B6: BILL | C6: Online | D6: =1357 -> 1357 | H6: Personal | K6: EXPECTED AVAILABLE BALANCE: | L6: =L5 - D68 + (SUMIFS(D2:D30, B2:B30, "=TEMP")) -> 998
A7: KAKA Flight EMI | C7: Online | D7: 2460 | H7: Temp
A8: Family | B8: FAMILY | C8: Online | D8: 20000 | H8: Family
A9: UCO Bank | B9: EMI | C9: Online | D9: 500
A10: Cook | B10: FAMILY | C10: Online | D10: 4000
A11: Maa | B11: Maa | C11: Online | D11: 6000
A12: SIP Temp | B12: TEMP | C12: Online | D12: 2500
A13: SIP | B13: SAVINGS | C13: Online | D13: 5000 | G13: Personal Expenses
A14: CC Bill (RBL) | B14: CC | C14: Online | D14: 2785 | G14: Type | H14: Date | I14: Amount
A15: Bangalore expenses | B15: PERSONAL | C15: Online | D15: =I32 -> 2885.8 | G15: Food
A16: CC Bill (HDFC) | B16: CC | C16: Online | D16: 5232 | G16: Company Food | I16: =131+100+142 -> 373
A17: Flat rent | B17: BANGALORE | C17: Online | D17: 20000 | G17: Rapido | I17: =281+205+62+105+115+47+35+41 -> 891
A18: Electricity | B18: BILL | C18: Online | D18: =320 -> 320 | G18: Refreshment | I18: =(15*6)+20+30+117+20 -> 277
A19: Electricity | B19: BILL | C19: Online | D19: =451 -> 451 | G19: FoodBook
A20: Savings | B20: SAVINGS | C20: Online | D20: =3812+2290 -> 6102 | G20: Misc | I20: =120+100+52-0.36 -> 271.64
G21: Grocery | I21: =310+10 -> 320
G22: Medicine | I22: =413.16 -> 413.16
G23: Chichek & Fish | I23: =240 -> 240
G24: Water | I24: =100 -> 100
G25: Gas
C32: TOTAL EXPENSE | D32: =SUM(D3:D30) -> 98159.8 | G32: Total | I32: =SUM(I15:I30) -> 2885.8
A35: PENDING
A36: PAYMENT REASON | B36: PAYMENT CATEGORY | D36: PAYMENT AMOUNT
A37: MOBILE RECHARGE | B37: BILL | C37: Online | D37: 300
A38: Wifi | B38: BILL | C38: Online | D38: =1157 -> 1157
A39: Personal Expenses | B39: PERSONAL | C39: Online | D39: =8000-D15 -> 5114.2
C68: PENDING EXPENSE | D68: =SUM(D37:D65) -> 6571.2
A71: Kaka | B71: PENDING | D71: =30000+16000 -> 46000
A72: Masi | B72: PENDING | D72: 50000
A73: Babu Kaka | B73: PENDING | D73: =(50000 - ('JAN-24'!D28)) -> 40000

Sheet FEB-25
A1: TOTAL EXPENSE LIST | K1: AVAILABLE FROM PREVIOUS MONTH: | L1: 1843
A2: PAYMENT REASON | B2: PAYMENT CATEGORY | C2: DATE | D2: PAYMENT AMOUNT | G2: Color Code | H2: Category | K2: INCOME IN CURRENT MONTH: | L2: 106303
A3: Wifi | B3: BILL | C3: Online | D3: 0 | H3: Bills & EMI
A4: Personal Expenses | B4: PERSONAL | C4: Online | D4: =I32 -> 2675 | H4: Savings | K4: TOTAL AVAILABLE: | L4: =L1 + L2 -> 108146
A5: CC Bill (AXIS) | B5: CC | C5: Online | D5: 14151 | H5: Maa | K5: CURRENT AVAILABLE BALANCE: | L5: =L4 - (D32) -> 7808
A6: Electricity | B6: BILL | C6: Online | D6: 2295 | H6: Personal | K6: EXPECTED AVAILABLE BALANCE: | L6: =L5 - D68 + (SUMIFS(D2:D30, B2:B30, "=TEMP")) -> 5683
A7: KAKA Flight EMI | C7: Online | D7: 2460 | H7: Temp
A8: Family | B8: FAMILY | C8: Online | D8: 20000 | H8: Family
A9: CC Bill (SBI) | B9: CC | C9: Online | D9: 9715
A10: CC Bill (RBL) | B10: CC | C10: Online | D10: 2772
A11: UCO Bank | B11: EMI | C11: Online | D11: 500
A12: Cook | B12: FAMILY | C12: Online | D12: 4000
A13: Maa | B13: Maa | C13: Online | D13: 4000 | G13: Personal Expenses
A14: SIP Temp | B14: TEMP | C14: Online | D14: 2500 | G14: Type | H14: Date | I14: Amount
A15: SIP | B15: SAVINGS | C15: Online | D15: 1000 | G15: Family | I15: =1680 -> 1680
A16: Biye | B16: FAMILY | C16: Cash | D16: 7000 | G16: Company Food
A17: Saraswati Pujo Donation | B17: SOCIAL | C17: Online | D17: 400 | G17: Rapido
A18: CC Bill (HDFC) | B18: CC | C18: Online | D18: 6468 | G18: Refreshment
A19: Flat rent | B19: BANGALORE | C19: Online | D19: 20000 | G19: FoodBook
A20: Electricity | B20: BILL | C20: Online | D20: 402 | G20: Misc | I20: -5
G21: Grocery
G22: Medicine
G23: Chichek & Fish
G24: Water
G25: Gas
G26: Cash | I26: 1000
C32: TOTAL EXPENSE | D32: =SUM(D3:D30) -> 100338 | G32: Total | I32: =SUM(I15:I30) -> 2675
A35: PENDING
A36: PAYMENT REASON | B36: PAYMENT CATEGORY | D36: PAYMENT AMOUNT
A37: MOBILE RECHARGE | B37: BILL | C37: Online | D37: 300
A38: Personal Expenses | B38: PERSONAL | C38: Online | D38: =7000-D4 -> 4325
C68: PENDING EXPENSE | D68: =SUM(D37:D65) -> 4625
A71: Kaka | B71: PENDING | D71: =30000+16000 -> 46000
A72: Masi | B72: PENDING | D72: 50000
A73: Babu Kaka | B73: PENDING | D73: =(50000 - ('JAN-24'!D28)) -> 40000

Sheet MAR-25
A1: TOTAL EXPENSE LIST | K1: AVAILABLE FROM PREVIOUS MONTH: | L1: 1843
A2: PAYMENT REASON | B2: PAYMENT CATEGORY | C2: DATE | D2: PAYMENT AMOUNT | G2: Color Code | H2: Category | K2: INCOME IN CURRENT MONTH: | L2: 106303
A3: Wifi | B3: BILL | C3: Online | D3: 1357 | H3: Bills & EMI
A4: CC Bill (AXIS-1) | B4: CC | C4: Online | D4: 10578 | H4: Savings | K4: TOTAL AVAILABLE: | L4: =L1 + L2 -> 108146
A5: CC Bill (SBI) | B5: CC | C5: Online | D5: 5641 | H5: Maa | K5: CURRENT AVAILABLE BALANCE: | L5: =L4 - (D32) -> 12014
A6: CC Bill (RBL) | B6: CC | C6: Online | D6: 2772 | H6: Personal | K6: EXPECTED AVAILABLE BALANCE: | L6: =L5 - D68 + (SUMIFS(D2:D30, B2:B30, "=TEMP")) -> 8214
A7: Electricity | B7: BILL | C7: Online | D7: 2295 | H7: Temp
A8: CC Bill (AXIS-2) | B8: CC | C8: Online | D8: 9164 | H8: Family
A9: CC Bill (HDFC) | B9: CC | C9: Online | D9: 3625
A10: Family | B10: FAMILY | C10: Online | D10: 25000
A11: Cook | B11: FAMILY | C11: Online | D11: 4000
A12: Maa | B12: Maa | C12: Online | D12: 6000
A13: SIP Temp | B13: TEMP | C13: Online | D13: 2500 | G13: Personal Expenses
A14: Flat rent | B14: BANGALORE | C14: Online | D14: 20000 | G14: Type | H14: Date | I14: Amount
A15: Electricity | B15: BILL | C15: Online | D15: 240 | G15: Food
A16: KAKA Flight EMI | C16: Online | D16: 2460 | G16: Company Food
A17: UCO Bank | B17: EMI | C17: Online | D17: 500 | G17: Rapido
G18: Refreshment
G19: FoodBook
G20: Misc
G21: Grocery
G22: Medicine
G23: Chichek & Fish
G24: Water
G25: Gas
C32: TOTAL EXPENSE | D32: =SUM(D3:D30) -> 96132 | G32: Total | I32: =SUM(I15:I30) -> 0
A35: PENDING
A36: PAYMENT REASON | B36: PAYMENT CATEGORY | D36: PAYMENT AMOUNT
A37: MOBILE RECHARGE | B37: BILL | C37: Online | D37: 300
A38: Personal Expenses | B38: PERSONAL | C38: Online | D38: 6000
A51: SIP | B51: SAVINGS | C51: Online | D51: 0
A52: Bangalore expenses | B52: PERSONAL | C52: Online | D52: =I32 -> 0
C68: PENDING EXPENSE | D68: =SUM(D37:D65) -> 6300
A71: Kaka | B71: PENDING | D71: =30000+16000 -> 46000
A72: Masi | B72: PENDING | D72: 50000
A73: Babu Kaka | B73: PENDING | D73: =(50000 - ('JAN-24'!D28)) -> 40000

Sheet APR-25
A1: TOTAL EXPENSE LIST | K1: AVAILABLE FROM PREVIOUS MONTH: | L1: 1690
A2: PAYMENT REASON | B2: PAYMENT CATEGORY | C2: DATE | D2: PAYMENT AMOUNT | G2: Color Code | H2: Category | K2: INCOME IN CURRENT MONTH: | L2: 112681
A3: Mobile Recharge(Rini Jio) | B3: BILL | C3: Online | D3: 199 | H3: Bills & EMI
A4: Rini | B4: FAMILY | C4: Online | D4: 500 | H4: Savings | K4: TOTAL AVAILABLE: | L4: =L1 + L2 -> 114371
A5: Mother's Hut | B5: FAMILY | C5: Online | D5: 1200 | H5: Maa | K5: CURRENT AVAILABLE BALANCE: | L5: =L4 - (D32) -> 12992
A6: CC Bill (AXIS-1) | B6: CC | C6: Online | D6: 11795 | H6: Personal | K6: EXPECTED AVAILABLE BALANCE: | L6: =L5 - D68 + (SUMIFS(D2:D30, B2:B30, "=TEMP")) -> 8891
A7: CC Bill (SBI) | B7: CC | C7: Online | D7: 4651 | H7: Temp
A8: CC Bill (RBL) | B8: CC | C8: Online | D8: 2757 | H8: Family
A9: CC Bill (AXIS-2) | B9: CC | C9: Online | D9: 1040
A10: Electricity | B10: BILL | C10: Online | D10: 2295
A11: Wifi | B11: BILL | C11: Online | D11: 1357
A12: Family | B12: FAMILY | C12: Online | D12: 25540
A13: KAKA Flight EMI | C13: Online | D13: 2460 | G13: Personal Expenses
A14: UCO Bank | B14: EMI | C14: Online | D14: 500 | G14: Type | H14: Date | I14: Amount
A15: Cook | B15: FAMILY | C15: Cash | D15: 4000 | G15: Food
A16: Maa | B16: Maa | C16: Cash | D16: 6000 | G16: Company Food
A17: SIP Temp | B17: TEMP | C17: Online | D17: 2500 | G17: Rapido
A18: SIP | B18: SAVINGS | C18: Online | D18: 5000 | G18: Refreshment
A19: Flat rent | B19: BANGALORE | C19: Online | D19: 20000 | G19: FoodBook
A20: CC Bill (HDFC) | B20: CC | C20: Online | D20: 9200 | G20: Misc
A21: Electricity | B21: BILL | C21: Online | D21: 385 | G21: Grocery
G22: Medicine
G23: Chichek & Fish
G24: Water
G25: Gas
C32: TOTAL EXPENSE | D32: =SUM(D3:D30) -> 101379 | G32: Total | I32: =SUM(I15:I30) -> 0
A35: PENDING
A36: PAYMENT REASON | B36: PAYMENT CATEGORY | D36: PAYMENT AMOUNT
A37: MOBILE RECHARGE | B37: BILL | C37: Online | D37: =500-D3 -> 301
A38: Personal Expenses | B38: PERSONAL | C38: Online | D38: =2000-(D4 + D5) -> 300
A40: Bangalore expenses | B40: PERSONAL | C40: Online | D40: 6000
C68: PENDING EXPENSE | D68: =SUM(D37:D60) -> 6601
A71: Kaka | B71: PENDING | D71: =30000+16000 -> 46000
A72: Masi | B72: PENDING | D72: 50000
A73: Babu Kaka | B73: PENDING | D73: =(50000 - ('JAN-24'!D28)) -> 40000

Sheet MAY-25
A1: TOTAL EXPENSE LIST | K1: AVAILABLE FROM PREVIOUS MONTH: | L1: 744
A2: PAYMENT REASON | B2: PAYMENT CATEGORY | C2: DATE | D2: PAYMENT AMOUNT | G2: Color Code | H2: Category | K2: INCOME IN CURRENT MONTH: | L2: 118603
A3: CC Bill (AXIS-1) | B3: CC | C3: Online | D3: 10923 | H3: Bills & EMI
A4: CC Bill (SBI) | B4: CC | C4: Online | D4: 5540 | H4: Savings | K4: TOTAL AVAILABLE: | L4: =L1 + L2 -> 119347
A5: CC Bill (RBL) | B5: CC | C5: Online | D5: 2745 | H5: Maa | K5: CURRENT AVAILABLE BALANCE: | L5: =L4 - (D32) -> 7558
A6: CC Bill (AXIS-2) | B6: CC | C6: Online | D6: 3902 | H6: Personal | K6: EXPECTED AVAILABLE BALANCE: | L6: =L5 - D68 + (SUMIFS(D2:D30, B2:B30, "=TEMP")) -> 1357
A7: Bangalore Wifi | B7: BILL | C7: Online | D7: 814 | H7: Temp
A8: Electricity | B8: BILL | C8: Online | D8: 2783 | H8: Family
A9: UCO Bank | B9: EMI | C9: Online | D9: 500
A10: Cook | B10: FAMILY | C10: Online | D10: 4000
A11: Maa | B11: Maa | C11: Online | D11: 4000
A12: Family | B12: FAMILY | C12: Online | D12: 20000
A13: KAKA Flight EMI | C13: Online | D13: 2500 | G13: Personal Expenses
A14: SIP Temp | B14: TEMP1 | C14: Online | D14: 2500 | G14: Type | H14: Date | I14: Amount
A15: SIP | B15: SAVINGS | C15: Online | D15: 5000 | G15: Food | I15: =140 -> 140
A16: SAVINGS | B16: SAVINGS | C16: Online | D16: 9000 | G16: Company Food | I16: =146+162 -> 308
A17: Home EMI | B17: BILL | C17: Online | D17: =(3556+236)+(2792) -> 6584 | G17: Rapido
A18: Bangalore Expense | B18: PERSONAL | C18: Online | D18: =I32 -> 3799 | G18: Refreshment
A19: CC Bill (HDFC) | B19: CC | C19: Online | D19: 6152 | G19: FoodBook
G20: Misc | I20: =84 -> 84
A21: Electricity | B21: BILL | C21: Online | D21: 1047 | G21: Grocery | I21: =239+75+100+50+270 -> 734
A22: Flat rent | B22: BANGALORE | C22: Online | D22: 20000 | G22: Medicine | I22: =783 -> 783
G23: Chicken & Fish
G24: Water
G25: Gas | I25: 400
G26: Mobile Battery | I26: 1200
G27: College | I27: 150
C32: TOTAL EXPENSE | D32: =SUM(D3:D30) -> 111789 | G32: Total | I32: =SUM(I15:I30) -> 3799
A35: PENDING
A36: PAYMENT REASON | B36: PAYMENT CATEGORY | D36: PAYMENT AMOUNT
A37: MOBILE RECHARGE | B37: BILL | C37: Online | D37: 0
A38: Personal Expenses | B38: PERSONAL | C38: Online | D38: 0
A39: Bangalore expenses | B39: PERSONAL | C39: Online | D39: =10000-(D18) -> 6201
C68: PENDING EXPENSE | D68: =SUM(D37:D60) -> 6201
A71: Kaka | B71: PENDING | D71: =30000+16000 -> 46000
A72: Masi | B72: PENDING | D72: 50000
A73: Babu Kaka | B73: PENDING | D73: =(50000 - ('JAN-24'!D28)) -> 40000

Sheet JUN-25
A1: TOTAL EXPENSE LIST | K1: AVAILABLE FROM PREVIOUS MONTH: | L1: 2518
A2: PAYMENT REASON | B2: PAYMENT CATEGORY | C2: DATE | D2: PAYMENT AMOUNT | G2: Color Code | H2: Category | K2: INCOME IN CURRENT MONTH: | L2: 226863
A3: Bangalore Expense | B3: PERSONAL | C3: Online | D3: =I32 -> 1569 | H3: Bills & EMI
A4: CC Bill (AXIS-1) | B4: CC | C4: Online | D4: 11009 | H4: Savings | K4: TOTAL AVAILABLE: | L4: =L1 + L2 -> 229381
A5: CC Bill (SBI) | B5: CC | C5: Online | D5: 3743 | H5: Maa | K5: CURRENT AVAILABLE BALANCE: | L5: =L4 - (D32) -> 5232
A6: CC Bill (RBL) | B6: CC | C6: Online | D6: 2737 | H6: Personal | K6: EXPECTED AVAILABLE BALANCE: | L6: =L5 - D68 + (SUMIFS(D2:D30, B2:B30, "=TEMP")) -> 158
A7: CC Bill (AXIS-2) | B7: CC | C7: Online | D7: 4930 | H7: Temp
A8: Wifi (Home) | B8: TEMP | C8: Online | D8: 1357 | H8: Family
A9: Electricity (HOME) | B9: BILL | C9: Online | D9: 2782
A10: SIP Temp | B10: TEMP1 | C10: Online | D10: 2500
A11: SIP | B11: SAVINGS | C11: Online | D11: 5000
A12: SAVINGS | B12: SAVINGS | C12: Online | D12: 20000
A13: Home EMI | B13: BILL | C13: Online | D13: =(3556)+(2556) -> 6112 | G13: Personal Expenses
A14: Family | B14: FAMILY | C14: Online | D14: 20000 | G14: Type | H14: Date | I14: Amount
A15: KAKA Flight EMI | C15: Online | D15: =2500+1500 -> 4000 | G15: Food
A16: UCO Bank | B16: EMI | C16: Online | D16: 500 | G16: Company Food | I16: =197+119+131+122 -> 569
A17: Bappa Kaka | B17: SOCIAL | C17: Online | D17: 100000 | G17: Rapido
A18: Cook | B18: FAMILY | C18: Online | D18: 4000 | G18: Refreshment | I18: =190+10 -> 200
A19: Maa | B19: Maa | C19: Online | D19: 6000 | G19: FoodBook
A20: Flat rent | B20: BANGALORE | C20: Online | D20: 20000 | G20: Misc | I20: =2+409 -> 411
A21: CC Bill (HDFC) | B21: CC | C21: Online | D21: 5090 | G21: Grocery | I21: =147+13 -> 160
A22: Cash | B22: PERSONAL | D22: 2000 | G22: Medicine | I22: =29 -> 29
A23: Electricity (FLAT) | B23: BILL | C23: Online | D23: 820 | G23: Chicken & Fish
G24: Water | I24: =110 -> 110
G25: Gas
G26: Mobile Battery
G27: College
G28: Hair Cream | I28: 90
C32: TOTAL EXPENSE | D32: =SUM(D3:D30) -> 224149 | G32: Total | I32: =SUM(I15:I30) -> 1569
A35: PENDING
A36: PAYMENT REASON | B36: PAYMENT CATEGORY | D36: PAYMENT AMOUNT
A37: MOBILE RECHARGE | B37: BILL | C37: Online | D37: 0
A38: Personal Expenses | B38: PERSONAL | C38: Online | D38: 0
A39: Bangalore expenses | B39: PERSONAL | C39: Online | D39: =8000-D3 -> 6431
C68: PENDING EXPENSE | D68: =SUM(D37:D65) -> 6431
A71: Kaka | B71: PENDING | D71: =30000+16000 -> 46000
A72: Masi | B72: PENDING | D72: 50000
A73: Babu Kaka | B73: PENDING | D73: =(50000 - ('JAN-24'!D28)) -> 40000
A74: Bappa Kaka | B74: PENDING | D74: =270000-D17 -> 170000

Sheet JUL-25
A1: TOTAL EXPENSE LIST | K1: AVAILABLE FROM PREVIOUS MONTH: | L1: 2215
A2: PAYMENT REASON | B2: PAYMENT CATEGORY | C2: DATE | D2: PAYMENT AMOUNT | G2: Color Code | H2: Category | K2: INCOME IN CURRENT MONTH: | L2: 118603
A3: CC Bill (AXIS-1) | B3: CC | C3: Online | D3: 16156 | H3: Bills & EMI
A4: CC Bill (SBI) | B4: CC | C4: Online | D4: 5476 | H4: Savings | K4: TOTAL AVAILABLE: | L4: =L1 + L2 -> 120818
A5: CC Bill (RBL) | B5: CC | C5: Online | D5: 3318 | H5: Maa | K5: CURRENT AVAILABLE BALANCE: | L5: =L4 - (D32) -> 10123
A6: CC Bill (AXIS-2) | B6: CC | C6: Online | D6: 8482 | H6: Personal | K6: EXPECTED AVAILABLE BALANCE: | L6: =L5 - D68 + (SUMIFS(D2:D30, B2:B30, "=TEMP")) -> 2724
A7: Electricity (HOME) | B7: BILL | C7: Online | D7: 2783 | H7: Temp
A8: UCO Bank | B8: EMI | C8: Online | D8: 500 | H8: Family
A9: Family | B9: FAMILY | C9: Online | D9: 20000
A10: KAKA Flight EMI | C10: Online | D10: 3000
A11: Cook | B11: FAMILY | C11: Online | D11: 4000
A12: Maa | B12: Maa | C12: Online | D12: 4000
A13: SIP Temp | B13: TEMP1 | C13: Online | D13: 2500 | G13: Personal Expenses
A14: SIP | B14: SAVINGS | C14: Online | D14: 5000 | G14: Type | H14: Date | I14: Amount
A15: Home EMI | B15: BILL | C15: Online | D15: =(3556)+(2556) -> 6112 | G15: Food
A16: Bangalore Expense | B16: PERSONAL | C16: Online | D16: =I32 -> 601 | G16: Company Food | I16: =139+238+107 -> 484
A17: Flat rent | B17: BANGALORE | C17: Online | D17: 20000 | G17: Rapido
A18: CC Bill (HDFC) | B18: CC | C18: Online | D18: 7862 | G18: Refreshment | I18: =10 -> 10
A19: Electricity (FLAT) | B19: BILL | C19: Online | D19: 905 | G19: FoodBook
G20: Misc
G21: Grocery | I21: =107 -> 107
G22: Medicine
G23: Chicken & Fish
G24: Water
G25: Gas
G26: Mobile Battery
G27: College
G28: Hair Cream
C32: TOTAL EXPENSE | D32: =SUM(D3:D30) -> 110695 | G32: Total | I32: =SUM(I15:I30) -> 601
A35: PENDING
A36: PAYMENT REASON | B36: PAYMENT CATEGORY | D36: PAYMENT AMOUNT
A37: SAVINGS | B37: SAVINGS | C37: Online | D37: 0
A38: Wifi (Home) | B38: TEMP | C38: Online | D38: 0
A39: Bangalore expenses | B39: PERSONAL | C39: Online | D39: =8000-D16 -> 7399
C68: PENDING EXPENSE | D68: =SUM(D37:D65) -> 7399
A71: Kaka | B71: PENDING | D71: =30000+16000 -> 46000
A72: Masi | B72: PENDING | D72: 50000
A73: Babu Kaka | B73: PENDING | D73: =(50000 - ('JAN-24'!D28)) -> 40000
A74: Bappa Kaka | B74: PENDING | D74: =270000-100000 -> 170000

Sheet AUG-25
A1: TOTAL EXPENSE LIST | K1: AVAILABLE FROM PREVIOUS MONTH: | L1: 5384
A2: PAYMENT REASON | B2: PAYMENT CATEGORY | C2: DATE | D2: PAYMENT AMOUNT | G2: Color Code | H2: Category | K2: INCOME IN CURRENT MONTH: | L2: 155244
A3: Bangalore Expense | C3: Online | D3: =I32 -> 2077 | H3: Bills & EMI
A4: CC Bill (AXIS-1) | B4: CC | C4: Online | D4: 13058 | H4: Savings | K4: TOTAL AVAILABLE: | L4: =L1 + L2 -> 160628
A5: CC Bill (SBI) | B5: CC | C5: Online | D5: 8423 | H5: Maa | K5: CURRENT AVAILABLE BALANCE: | L5: =L4 - (D32) -> 10129
A6: CC Bill (AXIS-2) | B6: CC | C6: Online | D6: 7232 | H6: Personal | K6: EXPECTED AVAILABLE BALANCE: | L6: =L5 - D68 + (SUMIFS(D2:D30, B2:B30, "=TEMP")) -> 2849
A7: Electricity (HOME) | B7: BILL | C7: Online | D7: 3104 | H7: Temp
A8: UCO Bank | B8: EMI | C8: Online | D8: 500 | H8: Family
A9: Cook | B9: FAMILY | C9: Online | D9: 4000
A10: Maa | B10: Maa | C10: Online | D10: 4000
A11: Family | B11: FAMILY | C11: Online | D11: 21000
A12: KAKA Flight EMI | C12: Online | D12: 3000
A13: SIP Temp | B13: TEMP1 | C13: Online | D13: 2500 | G13: Personal Expenses
A14: SIP | B14: SAVINGS | C14: Online | D14: 5000 | G14: Type | H14: Date | I14: Amount
A15: Home EMI | B15: BILL | C15: Online | D15: =(3556)+(2556) -> 6112 | G15: Food | I15: =130+685 -> 815
A16: Rini Mobile | B16: EMI | C16: Online | D16: 2178 | G16: Company Food | I16: =135+139+157+144 -> 575
A17: Arghya | C17: Online | D17: =5678+824 -> 6502 | G17: Rapido
A18: Deep | C18: Online | D18: 10000 | G18: Refreshment | I18: =120+70 -> 190
A19: Savings | B19: SAVINGS | C19: Online | D19: 25000 | G19: FoodBook
A20: Flat rent | B20: BANGALORE | C20: Online | D20: 20000 | G20: Misc | I20: =225 -> 225
A21: CC Bill (HDFC) | B21: CC | C21: Online | D21: 5908 | G21: Grocery | I21: =62 -> 62
A22: Electricity (FLAT) | B22: BILL | C22: Online | D22: 905 | G22: Medicine | I22: =100 -> 100
G23: Chicken & Fish
G24: Water | I24: =110 -> 110
G25: Gas
G26: Mobile Battery
C32: TOTAL EXPENSE | D32: =SUM(D3:D30) -> 150499 | G32: Total | I32: =SUM(I15:I30) -> 2077
A35: PENDING
A36: PAYMENT REASON | B36: PAYMENT CATEGORY | D36: PAYMENT AMOUNT
A37: Wifi (Home) | B37: TEMP | C37: Online | D37: 1357
A38: Bangalore expenses | B38: PERSONAL | C38: Online | D38: =8000-D3 -> 5923
C68: PENDING EXPENSE | D68: =SUM(D37:D65) -> 7280
A71: Kaka | B71: PENDING | D71: =30000+16000 -> 46000
A72: Masi | B72: PENDING | D72: 50000
A73: Babu Kaka | B73: PENDING | D73: =(50000 - ('JAN-24'!D28)) -> 40000
A74: Bappa Kaka | B74: PENDING | D74: =270000-100000 -> 170000
A75: Sanjoy Kaka | B75: PENDING | D75: 30000
A76: Bank | B76: PENDING | D76: 14000
D82: =SUM(D71:D76) -> 350000

Sheet SEP-25
A1: TOTAL EXPENSE LIST | K1: AVAILABLE FROM PREVIOUS MONTH: | L1: 1712
A2: PAYMENT REASON | B2: PAYMENT CATEGORY | C2: DATE | D2: PAYMENT AMOUNT | G2: Color Code | H2: Category | K2: INCOME IN CURRENT MONTH: | L2: =1357+156849 -> 158206
A3: CC Bill (AXIS-1) | B3: CC | C3: Online | D3: 20219 | H3: Bills & EMI
A4: CC Bill (SBI) | B4: CC | C4: Online | D4: 8804 | H4: Savings | K4: TOTAL AVAILABLE: | L4: =L1 + L2 -> 159918
A5: CC Bill (AXIS-2) | B5: CC | C5: Online | D5: 24752 | H5: Maa | K5: CURRENT AVAILABLE BALANCE: | L5: =L4 - (D32) -> 18919
A6: Electricity (HOME) | B6: BILL | C6: Online | D6: 3104 | H6: Personal | K6: EXPECTED AVAILABLE BALANCE: | L6: =L5 - D68 + (SUMIFS(D2:D30, B2:B30, "=TEMP")) -> 10875
A7: UCO Bank | B7: EMI | C7: Online | D7: 500 | H7: Temp
A8: Cook | B8: FAMILY | C8: Online | D8: 4000 | H8: Family
A9: Maa | B9: Maa | C9: Online | D9: 6000
A10: SIP Temp | B10: TEMP1 | C10: Online | D10: 2500
A11: SIP | B11: SAVINGS | C11: Online | D11: 5500
A12: Home EMI | B12: BILL | C12: Online | D12: =(3556)+(2556) -> 6112
A13: Rini Mobile | B13: EMI | C13: Online | D13: 2178 | G13: Personal Expenses
A14: CC Bill (HDFC) | B14: CC | C14: Online | D14: 6207 | G14: Type | H14: Date | I14: Amount
A15: Family | B15: FAMILY | C15: Online | D15: 21000 | G15: Food
A16: KAKA Flight EMI | C16: Online | D16: 3000 | G16: Company Food | I16: =139+98 -> 237
A17: Bangalore Expenses | B17: PERSONAL | C17: Online | D17: =I32 -> 1956 | G17: Rapido | I17: =73+90+52 -> 215
A18: Arghya | C18: Online | D18: =4031+274-5 -> 4300 | G18: Refreshment | I18: =100+20+30 -> 150
A19: Pujo Shopping | B19: TEMP | C19: Online | D19: 0 | G19: FoodBook
A20: Flat rent | B20: BANGALORE | C20: Online | D20: 20000 | G20: Misc | I20: -39
A21: Electricity (FLAT) | B21: BILL | C21: Online | D21: 867 | G21: Grocery | I21: =149+180+945 -> 1274
G22: Medicine | I22: =119 -> 119
G23: Chicken & Fish
G24: Water
G25: Gas
G26: Mobile Battery
C32: TOTAL EXPENSE | D32: =SUM(D3:D30) -> 140999 | G32: Total | I32: =SUM(I15:I30) -> 1956
A35: PENDING
A36: PAYMENT REASON | B36: PAYMENT CATEGORY | D36: PAYMENT AMOUNT
A38: Bangalore expenses | B38: PERSONAL | C38: Online | D38: =10000-D17 -> 8044
A55: Savings | B55: SAVINGS | C55: Online
C68: PENDING EXPENSE | D68: =SUM(D37:D65) -> 8044
A71: Kaka | B71: PENDING | D71: =30000+16000 -> 46000
A72: Masi | B72: PENDING | D72: 50000
A73: Babu Kaka | B73: PENDING | D73: =(50000 - ('JAN-24'!D28)) -> 40000
A74: Bappa Kaka | B74: PENDING | D74: =270000-100000 -> 170000
A75: Sanjoy Kaka | B75: PENDING | D75: 15000
D82: =SUM(D71:D76) -> 321000

Sheet OCT-25
A1: TOTAL EXPENSE LIST | K1: AVAILABLE FROM PREVIOUS MONTH: | L1: =8494-1507+2200 -> 9187
A2: PAYMENT REASON | B2: PAYMENT CATEGORY | C2: DATE | D2: PAYMENT AMOUNT | G2: Color Code | H2: Category | K2: INCOME IN CURRENT MONTH: | L2: =155388+1257 -> 156645
A3: CC Bill (AXIS-1) | B3: CC | C3: Online | D3: 10317 | H3: Bills & EMI
A4: CC Bill (SBI) | B4: CC | C4: Online | D4: 5832 | H4: Savings | K4: TOTAL AVAILABLE: | L4: =L1 + L2 -> 165832
A5: CC Bill (AXIS-2) | B5: CC | C5: Online | D5: 8682 | H5: Maa | K5: CURRENT AVAILABLE BALANCE: | L5: =L4 - (D32) -> 9734
A6: Family | B6: FAMILY | C6: Online | D6: 25000 | H6: Personal | K6: EXPECTED AVAILABLE BALANCE: | L6: =L5 - D68 + (SUMIFS(D2:D30, B2:B30, "=TEMP")) -> 5641
A7: KAKA Flight EMI | C7: Online | D7: 3000 | H7: Temp
A8: AddaTimes | D8: 699 | H8: Family
A9: UCO Bank | B9: EMI | C9: Online | D9: 500
A10: Electricity (HOME) | B10: BILL | C10: Online | D10: 3104
A11: Bangalore Expenses | D11: =I32 -> 5907
A12: SIP Temp | B12: TEMP1 | C12: Online | D12: 2500
A13: SIP | B13: SAVINGS | C13: Online | D13: 5500 | G13: Personal Expenses
A14: Home EMI | B14: BILL | C14: Online | D14: =(3556)+(2556) -> 6112 | G14: Type | H14: Date | I14: Amount
A15: Rini Mobile | B15: EMI | C15: Online | D15: 2178 | G15: Food
A16: Arghya | C16: Online | D16: 275 | G16: Company Food | I16: =135+139+122+119 -> 515
A17: Savings | B17: PERSONAL | C17: Online | D17: =32000+300 -> 32300 | G17: Rapido | I17: =40+242+227+200+40+40+50+40+43+100+54+435+115+242+47+40+47+40+53 -> 2095
A18: Cook | B18: FAMILY | C18: Online | D18: 4000 | G18: Refreshment
A19: Maa | B19: Maa | C19: Online | D19: 8000 | G19: FoodBook
A20: CC Bill (HDFC) | B20: CC | C20: Online | D20: 6554 | G20: Misc | I20: =300 -> 300
A21: Flat rent | B21: BANGALORE | C21: Online | D21: 20000 | G21: Grocery | I21: =220+120 -> 340
A22: MicroOven | B22: BANGALORE | C22: Online | D22: 2300 | G22: Medicine | I22: =140 -> 140
A23: Rini GATE | B23: FAMILY | C23: Online | D23: 1000 | G23: Chicken & Fish | I23: =264+220 -> 484
A24: Vasanth Farewell | B24: SOCIAL | C24: Online | D24: 500 | G24: Water | I24: =110 -> 110
A25: Electricity (FLAT) | B25: BILL | C25: Online | D25: 911 | G25: Gas
A26: Maa Mobile recharge | B26: BILL | C26: Online | D26: =199+189 -> 388 | G26: Saloon | I26: 600
A27: Mobile recharge | B27: BILL | C27: Online | D27: =77+189-1 -> 265 | G27: Sandel | I27: 280
A28: Train Ticket | B28: FAMILY | C28: Online | D28: 274 | G28: Office Party | I28: 1043
C32: TOTAL EXPENSE | D32: =SUM(D3:D30) -> 156098 | G32: Total | I32: =SUM(I15:I30) -> 5907
A35: PENDING
A36: PAYMENT REASON | B36: PAYMENT CATEGORY | D36: PAYMENT AMOUNT
A38: Personal expenses | B38: PERSONAL | C38: Online | D38: =10000-D11 -> 4093
C68: PENDING EXPENSE | D68: =SUM(D37:D65) -> 4093
A71: Kaka | B71: PENDING | D71: =30000+16000 -> 46000
A72: Masi | B72: PENDING | D72: 50000
A73: Babu Kaka | B73: PENDING | D73: =(50000 - ('JAN-24'!D28)) -> 40000
A74: Bappa Kaka | B74: PENDING | D74: =270000-100000 -> 170000
A75: Sanjoy Kaka | B75: PENDING | D75: 15000
D82: =SUM(D71:D76) -> 321000

Sheet NOV-25
A1: TOTAL EXPENSE LIST | K1: AVAILABLE FROM PREVIOUS MONTH: | L1: =1520+2272 -> 3792
A2: PAYMENT REASON | B2: PAYMENT CATEGORY | C2: DATE | D2: PAYMENT AMOUNT | G2: Color Code | H2: Category | K2: INCOME IN CURRENT MONTH: | L2: =155243+1357 -> 156600
A3: CC Bill (AXIS-1) | B3: CC | C3: Online | D3: 11059 | H3: Bills & EMI
A4: CC Bill (SBI) | B4: CC | C4: Online | D4: 4285 | H4: Savings | K4: TOTAL AVAILABLE: | L4: =L1 + L2 -> 160392
A5: CC Bill (AXIS-2) | B5: CC | C5: Online | D5: 9890 | H5: Maa | K5: CURRENT AVAILABLE BALANCE: | L5: =L4 - (D32) -> 16964
A6: Family | B6: FAMILY | C6: Online | D6: 25000 | H6: Personal | K6: EXPECTED AVAILABLE BALANCE: | L6: =L5 - D68 + (SUMIFS(D2:D30, B2:B30, "=TEMP")) -> 6964
A7: Cash | B7: FAMILY | C7: Cash | D7: 11000 | H7: Temp
A8: UCO Bank | B8: EMI | C8: Online | D8: 500 | H8: Family
A9: SIP Temp | B9: TEMP1 | C9: Online | D9: 2500
A10: SIP | B10: SAVINGS | C10: Online | D10: 5500
A11: Home EMI | B11: BILL | C11: Online | D11: =(3556)+(2556) -> 6112
A12: Rini Mobile | B12: EMI | C12: Online | D12: 2178
A13: Savings | B13: PERSONAL | C13: Online | D13: 20000 | G13: Personal Expenses
A14: Personal Expenses | B14: PERSONAL | C14: Online | D14: =I32 -> 3594 | G14: Type | H14: Date | I14: Amount
A15: Cook | B15: FAMILY | C15: Online | D15: 4000 | G15: Food
A16: CC Bill (HDFC) | B16: CC | C16: Online | D16: 5820 | G16: Company Food | I16: =135 -> 135
A17: Maa | B17: Maa | C17: Online | D17: 4000 | G17: Rapido | I17: =290+220+57+40+1250 -> 1857
A18: Electricity (HOME) | B18: BILL | C18: Online | D18: 1983 | G18: Refreshment
A19: Flat rent | B19: BANGALORE | C19: Online | D19: 20000 | G19: FoodBook
A20: Jogoddhatri Pujo (Chanda) | C20: Online | D20: 5000 | G20: Misc | I20: =160+517 -> 677
A21: Mobile Recharge | D21: =189 -> 189 | G21: Grocery | I21: =185 -> 185
A22: Electricity (FLAT) | B22: BILL | C22: Online | D22: 818 | G22: Medicine | I22: =200+30 -> 230
G23: Chicken & Fish
G24: Water | I24: =110 -> 110
G25: Gas
G26: Office Party | L26: 16964
G27: Wash | I27: 400
C32: TOTAL EXPENSE | D32: =SUM(D3:D30) -> 143428 | G32: Total | I32: =SUM(I15:I30) -> 3594
A35: PENDING
A36: PAYMENT REASON | B36: PAYMENT CATEGORY | D36: PAYMENT AMOUNT
A38: Personal expenses | B38: PERSONAL | C38: Online | D38: =10000-D41 -> 3594
A39: KAKA Flight EMI | B39: TEMP | C39: Online | D39: 0
A41: Bangalore Expenses | D41: =10000-I32 -> 6406
C68: PENDING EXPENSE | D68: =SUM(D37:D65) -> 10000
A71: Kaka | B71: PENDING | D71: =30000+16000 -> 46000
A72: Masi | B72: PENDING | D72: 50000
A73: Babu Kaka | B73: PENDING | D73: =(50000 - ('JAN-24'!D28)) -> 40000
A74: Bappa Kaka | B74: PENDING | D74: =270000-100000 -> 170000
D82: =SUM(D71:D76) -> 306000

Sheet DEC-25
A1: TOTAL EXPENSE LIST | K1: AVAILABLE FROM PREVIOUS MONTH: | L1: 12483
A2: PAYMENT REASON | B2: PAYMENT CATEGORY | C2: DATE | D2: PAYMENT AMOUNT | G2: Color Code | H2: Category | K2: INCOME IN CURRENT MONTH: | L2: =167009+1357 -> 168366
A3: CC Bill (AXIS-1) | B3: CC | C3: Online | D3: 10813 | H3: Bills & EMI
A4: WiFi (Bangalore) | B4: BILL | C4: Online | D4: 1178 | H4: Savings | K4: TOTAL AVAILABLE: | L4: =L1 + L2 -> 180849
A5: Personal Expenses | B5: PERSONAL | C5: Online | D5: =I32 -> 2588 | H5: Maa | K5: CURRENT AVAILABLE BALANCE: | L5: =L4 - (D32) -> 19319
A6: CC Bill (SBI) | B6: CC | C6: Online | D6: 19131 | H6: Personal | K6: EXPECTED AVAILABLE BALANCE: | L6: =L5 - D68 + (SUMIFS(D2:D30, B2:B30, "=TEMP")) -> 111
A7: Temp | B7: TEMP | C7: Online | D7: =15522 -> 15522 | H7: Temp
A8: Cook | B8: FAMILY | C8: Online | D8: 4000 | H8: Family
A9: Maa | B9: Maa | C9: Online | D9: 4000
A10: Electricity (HOME) | B10: BILL | C10: Online | D10: 1982
A11: Family | B11: FAMILY | C11: Online | D11: 25000
A12: SIP Temp | B12: TEMP1 | C12: Online | D12: 2500
A13: SIP | B13: SAVINGS | C13: Online | D13: 5500 | G13: Personal Expenses
A14: Home EMI | B14: BILL | C14: Online | D14: =(3556)+(2556) -> 6112 | G14: Type | H14: Date | I14: Amount
A15: Rini Mobile | B15: EMI | C15: Online | D15: 2178 | G15: Food
A16: CC Bill (AXIS-2) | B16: CC | C16: Online | D16: 14656 | G16: Company Food | I16: =177+193 -> 370
A17: Arghya | B17: PERSONAL | C17: Online | D17: 1370 | G17: Rapido | I17: =290+221+255+285+40+40+40+46 -> 1217
A18: Savings | B18: SAVINGS | C18: Online | D18: 45000 | G18: Refreshment | I18: =200 -> 200
G19: FoodBook
G20: Misc
G21: Grocery | I21: =172+440 -> 612
G22: Medicine
G23: Chicken & Fish
G24: Water
G25: Gas
G26: Office Party | L26: 16964
G28: Mobile recharge | I28: =189 -> 189
C32: TOTAL EXPENSE | D32: =SUM(D3:D30) -> 161530 | G32: Total | I32: =SUM(I15:I30) -> 2588
A35: PENDING
A36: PAYMENT REASON | B36: PAYMENT CATEGORY | D36: PAYMENT AMOUNT
A38: Personal expenses | B38: PERSONAL | C38: Online | D38: =10000-D5 -> 7412
A39: UCO Bank | B39: EMI | C39: Online | D39: 500
A41: CC Bill (HDFC) | B41: CC | C41: Online | D41: 6000
A42: Flat rent | B42: BANGALORE | C42: Online | D42: 20000
A43: Electricity (FLAT) | B43: BILL | C43: Online | D43: 818
C68: PENDING EXPENSE | D68: =SUM(D37:D65) -> 34730
A71: Kaka | B71: PENDING | D71: =30000+16000 -> 46000
A72: Masi | B72: PENDING | D72: 50000
A73: Babu Kaka | B73: PENDING | D73: =(50000 - ('JAN-24'!D28)) -> 40000
A74: Bappa Kaka | B74: PENDING | D74: =270000-100000-100000 -> 70000
A75: Arka | B75: PENDING | D75: 100000
D82: =SUM(D71:D76) -> 306000

Sheet JAN-26
A1: TOTAL EXPENSE LIST | K1: AVAILABLE FROM PREVIOUS MONTH: | L1: 704
A2: PAYMENT REASON | B2: PAYMENT CATEGORY | C2: DATE | D2: PAYMENT AMOUNT | G2: Color Code | H2: Category | K2: INCOME IN CURRENT MONTH: | L2: 155243
A3: CC Bill (AXIS-1) | B3: CC | C3: Online | D3: 7145 | H3: Bills & EMI
A4: WiFi (Bangalore) | B4: BILL | C4: Online | D4: 1178 | H4: Savings | K4: TOTAL AVAILABLE: | L4: =L1 + L2 -> 155947
A5: CC Bill (SBI) | B5: CC | C5: Online | D5: 2561 | H5: Maa | K5: CURRENT AVAILABLE BALANCE: | L5: =L4 - (D32) -> 33609
A6: Bangalore Expense | B6: PERSONAL | C6: Online | D6: =I32 -> 7501 | H6: Personal | K6: EXPECTED AVAILABLE BALANCE: | L6: =L5 - D68 + (SUMIFS(D2:D30, B2:B30, "=TEMP")) -> 27337
A7: Family | B7: FAMILY | C7: Online | D7: 25000 | H7: Temp
A8: Cook | B8: FAMILY | C8: Online | D8: 4000 | H8: Family
A9: Maa | B9: Maa | C9: Online | D9: 2000
A10: Electricity (HOME) | B10: BILL | C10: Online | D10: 1983
A11: SIP Temp | B11: TEMP1 | C11: Online | D11: 2500
A12: SIP | B12: SAVINGS | C12: Online | D12: 5500
A13: Home EMI | B13: BILL | C13: Online | D13: =(3556)+(2556) -> 6112 | G13: Personal Expenses
A14: Rini Mobile | B14: EMI | C14: Online | D14: 2178 | G14: Type | H14: Date | I14: Amount
A15: Flat rent | B15: BANGALORE | C15: Online | D15: 20000 | G15: Food | I15: =420+90 -> 510
A16: Electricity (FLAT) | B16: BILL | C16: Online | D16: 948 | G16: Company Food | I16: =488+55+144+144 -> 831
A17: Train | D17: 11050 | G17: Rapido | I17: =40+40+40+910+860+500+435+43+40 -> 2908
A18: CC Bill (HDFC) | B18: CC | C18: Online | D18: 9022 | G18: Refreshment | I18: =60 -> 60
A19: CC Bill (AXIS-2) | B19: CC | C19: Online | D19: 12660 | G19: FoodBook
A20: Maa | B20: Maa | C20: Online | D20: 1000 | G20: Misc | I20: =-10+120+120+100+942 -> 1272
G21: Grocery | I21: =200 -> 200
G22: Medicine | I22: =80+85+180+800 -> 1145
G23: Chicken & Fish
G24: Water | I24: =110 -> 110
G25: Gas
G26: Office Party | L26: 16964
G28: Mobile recharge | I28: =77+189+199 -> 465
C32: TOTAL EXPENSE | D32: =SUM(D3:D30) -> 122338 | G32: Total | I32: =SUM(I15:I30) -> 7501
A35: PENDING
A36: PAYMENT REASON | B36: PAYMENT CATEGORY | D36: PAYMENT AMOUNT
A38: Personal expenses | B38: PERSONAL | C38: Online | D38: =10000-D6 -> 2499
A39: UCO Bank | B39: EMI | C39: Online | D39: 500
A44: Family | B44: FAMILY | C44: Online | D44: 3000
A49: Arghya | B49: PERSONAL | C49: Online | D49: 273
A50: Savings | B50: SAVINGS | C50: Online | D50: 0
C68: PENDING EXPENSE | D68: =SUM(D37:D65) -> 6272
A71: Kaka | B71: PENDING | D71: =30000+16000 -> 46000
A72: Masi | B72: PENDING | D72: 50000
A73: Babu Kaka | B73: PENDING | D73: =(50000 - ('JAN-24'!D28)) -> 40000
A74: Bappa Kaka | B74: PENDING | D74: =270000-100000-100000 -> 70000
A75: Arka | B75: PENDING | D75: 100000
D82: =SUM(D71:D76) -> 306000

Sheet FEB-26
A1: TOTAL EXPENSE LIST | K1: AVAILABLE FROM PREVIOUS MONTH: | L1: 1000
A2: PAYMENT REASON | B2: PAYMENT CATEGORY | C2: DATE | D2: PAYMENT AMOUNT | G2: Color Code | H2: Category | K2: INCOME IN CURRENT MONTH: | L2: 155243
H3: Bills & EMI
A4: WiFi (Bangalore) | B4: BILL | C4: Online | D4: 1178 | H4: Savings | K4: TOTAL AVAILABLE: | L4: =L1 + L2 -> 156243
H5: Maa | K5: CURRENT AVAILABLE BALANCE: | L5: =L4 - (D32) -> 59210
A6: Bangalore Expense | B6: PERSONAL | C6: Online | D6: =I32 -> 528 | H6: Personal | K6: EXPECTED AVAILABLE BALANCE: | L6: =L5 - D68 + (SUMIFS(D2:D30, B2:B30, "=TEMP")) -> -33514
A7: Family | B7: FAMILY | C7: Online | D7: 25000 | H7: Temp
A8: Cook | B8: FAMILY | C8: Online | D8: 4000 | H8: Family
A9: Maa | B9: Maa | C9: Online | D9: 4000
A10: Electricity (HOME) | B10: BILL | C10: Online | D10: 1991
A11: SIP Temp | B11: TEMP1 | C11: Online | D11: 2500
A12: SIP | B12: SAVINGS | C12: Online | D12: 5500
G13: Personal Expenses
G14: Type | H14: Date | I14: Amount
A15: Flat rent | B15: BANGALORE | C15: Online | D15: 20000 | G15: Food
A16: Electricity (FLAT) | B16: BILL | C16: Online | D16: 948 | G16: Company Food | I16: =488 -> 488
G17: Rapido | I17: =40 -> 40
A18: CC Bill (HDFC) | B18: CC | C18: Online | D18: 9022 | G18: Refreshment
A19: CC Bill (AXIS-2) | B19: CC | C19: Online | D19: 12660 | G19: FoodBook
A20: CC Bill (AXIS-1) | B20: CC | C20: Online | D20: 7145 | G20: Misc
A21: CC Bill (SBI) | B21: CC | C21: Online | D21: 2561 | G21: Grocery
G22: Medicine
G23: Chicken & Fish
G24: Water
G25: Gas
G26: Office Party | L26: 16964
G28: Mobile recharge
C32: TOTAL EXPENSE | D32: =SUM(D4:D30) -> 97033 | G32: Total | I32: =SUM(I15:I30) -> 528
A35: PENDING
A36: PAYMENT REASON | B36: PAYMENT CATEGORY | D36: PAYMENT AMOUNT
A38: Personal expenses | B38: PERSONAL | C38: Online | D38: =10000-D6 -> 9472
A39: UCO Bank | B39: EMI | C39: Online | D39: 500
A41: CC Bill (HDFC) | B41: CC | C41: Online | D41: 6000
A42: Flat rent | B42: BANGALORE | C42: Online | D42: 20000
A43: Electricity (FLAT) | B43: BILL | C43: Online | D43: 818
A45: Cook | B45: FAMILY | C45: Online | D45: 4000
A46: Maa | B46: Maa | C46: Online | D46: 4000
A47: Electricity (HOME) | B47: BILL | C47: Online | D47: 1983
A48: Family | B48: FAMILY | C48: Online | D48: 25000
A49: SIP Temp | B49: TEMP1 | C49: Online | D49: 2500
A50: SIP | B50: SAVINGS | C50: Online | D50: 5500
A53: CC Bill (AXIS-2) | B53: CC | C53: Online | D53: 12678
A54: Arghya | B54: PERSONAL | C54: Online | D54: 273
A55: Savings | B55: SAVINGS | C55: Online | D55: 0
C68: PENDING EXPENSE | D68: =SUM(D37:D65) -> 92724
A71: Kaka | B71: PENDING | D71: =30000+16000 -> 46000
A72: Masi | B72: PENDING | D72: 50000
A73: Babu Kaka | B73: PENDING | D73: =(50000 - ('JAN-24'!D28)) -> 40000
A74: Bappa Kaka | B74: PENDING | D74: =270000-100000-100000 -> 70000
A75: Arka | B75: PENDING | D75: 100000
D82: =SUM(D71:D76) -> 306000

Sheet MAR-26
A1: TOTAL EXPENSE LIST | K1: AVAILABLE FROM PREVIOUS MONTH: | L1: =6130+506 -> 6636
A2: PAYMENT REASON | B2: PAYMENT CATEGORY | C2: DATE | D2: PAYMENT AMOUNT | G2: Color Code | H2: Category | K2: INCOME IN CURRENT MONTH: | L2: 389676
A3: Electricity (HOME) | B3: BILL | C3: Online | D3: 1992 | H3: Bills & EMI
A4: CC Bill (AXIS-2) | B4: CC | C4: Online | D4: 11132 | H4: Savings | K4: TOTAL AVAILABLE: | L4: =L1 + L2 -> 396312
A5: CC Bill (AXIS-1) | B5: CC | C5: Online | D5: 8409 | H5: Maa | K5: CURRENT AVAILABLE BALANCE: | L5: =L4 - (D32) -> -8928
A6: CC Bill (SBI) | B6: CC | C6: Online | D6: 2812 | H6: Personal | K6: EXPECTED AVAILABLE BALANCE: | L6: =L5 - D68 + (SUMIFS(D2:D30, B2:B30, "=TEMP")) -> -29869
A7: Bappa Kaka | D7: 100000 | H7: Temp
A8: Rini clz payment | D8: 1000 | H8: Family
A9: Cook | B9: FAMILY | C9: Online | D9: 4000
A10: Maa | B10: Maa | C10: Online | D10: 11000
A11: Family | B11: FAMILY | C11: Online | D11: 25000
A12: Arghya | B12: PERSONAL | C12: Online | D12: 822
A13: Bangalore Expenses | B13: PERSONAL | D13: =I32 -> 1237 | G13: Personal Expenses
A14: SIP Temp | B14: TEMP1 | C14: Online | D14: 2500 | G14: Type | H14: Date | I14: Amount
A15: SIP | B15: SAVINGS | C15: Online | D15: 5500 | G15: Food | I15: =339 -> 339
A16: Savings | B16: SAVINGS | C16: Online | D16: 65000 | G16: Company Food | I16: =97 -> 97
A17: ARKA | D17: 100000 | G17: Rapido | I17: =56+40 -> 96
A18: CC Bill (HDFC) | B18: CC | C18: Online | D18: 9502 | G18: Refreshment | I18: =10+20 -> 30
A19: Flat rent | B19: BANGALORE | C19: Online | D19: 20000 | G19: FoodBook
A20: UCO Bank | B20: EMI | C20: Online | D20: 500 | G20: Misc
A21: Electricity (FLAT) | B21: BILL | C21: Online | D21: 850 | G21: Grocery | I21: =65 -> 65
A22: Mother's Hut | D22: 1345 | G22: Medicine
A23: House of Commons | D23: 7639 | G23: Chicken & Fish
A24: Cake | G24: Water | I24: =110 -> 110
A25: Masi | D25: 25000 | G25: Gas | I25: 400
G26: Office Party | L26: 16964
G28: USB cable | I28: 100
C32: TOTAL EXPENSE | D32: =SUM(D3:D30) -> 405240 | G32: Total | I32: =SUM(I15:I30) -> 1237
A35: PENDING
A36: PAYMENT REASON | B36: PAYMENT CATEGORY | D36: PAYMENT AMOUNT
A37: WiFi (Bangalore) | B37: BILL | C37: Online | D37: 1178
A38: Personal expenses | B38: PERSONAL | C38: Online | D38: =12000-D13 -> 10763
A47: Aniversery party | D47: 9000
C68: PENDING EXPENSE | D68: =SUM(D37:D65) -> 20941
A71: Kaka | B71: PENDING | D71: =30000+16000 -> 46000
A72: Masi | B72: PENDING | D72: 50000
A73: Babu Kaka | B73: PENDING | D73: =(50000 - ('JAN-24'!D28)) -> 40000
A75: Arka | B75: PENDING | D75: 0
D82: =SUM(D71:D76) -> 136000

Sheet APR-26
A1: TOTAL EXPENSE LIST | K1: AVAILABLE FROM PREVIOUS MONTH: | L1: 10530
A2: PAYMENT REASON | B2: PAYMENT CATEGORY | C2: DATE | D2: PAYMENT AMOUNT | G2: Color Code | H2: Category | K2: INCOME IN CURRENT MONTH: | L2: 153330
A3: CC Bill (AXIS-2) | B3: CC | C3: Online | D3: 11563 | H3: Bills & EMI
A4: CC Bill (AXIS-1) | B4: CC | C4: Online | D4: 11010 | H4: Savings | K4: TOTAL AVAILABLE: | L4: =L1 + L2 -> 163860
A5: CC Bill (SBI) | B5: CC | C5: Online | D5: 7972 | H5: Maa | K5: CURRENT AVAILABLE BALANCE: | L5: =L4 - (D32) -> 8626
A6: Family | B6: FAMILY | C6: Online | D6: 25000 | H6: Personal | K6: EXPECTED AVAILABLE BALANCE: | L6: =L5 - D68 + (SUMIFS(D2:D30, B2:B30, "=TEMP")) -> 1598
A7: Arghya | B7: PERSONAL | C7: Online | D7: 3135 | H7: Temp
A8: Electricity (HOME) | B8: BILL | C8: Online | D8: 1984 | H8: Family
A9: SIP Temp | B9: TEMP1 | C9: Online | D9: 2500
A10: SIP | B10: SAVINGS | C10: Online | D10: 5500
A11: Savings | B11: SAVINGS | C11: Online | D11: 40000
A12: Bangalore Expenses | D12: =I32 -> 2972
A13: Cook | B13: FAMILY | C13: Online | D13: 4000 | G13: Personal Expenses
A14: Maa | B14: Maa | C14: Online | D14: 11000 | G14: Type | H14: Date | I14: Amount
A15: Flat rent | B15: BANGALORE | C15: Online | D15: 20000 | G15: Food | I15: =160 -> 160
A16: CC Bill (HDFC) | B16: CC | C16: Online | D16: 7085 | G16: Company Food
A17: Electricity (FLAT) | B17: BILL | C17: Online | D17: 1013 | G17: Rapido | I17: =222+310+215 -> 747
A18: UCO Bank | B18: EMI | C18: Online | D18: 500 | G18: Refreshment
G19: FoodBook
G20: Misc | I20: =-74 -> -74
G21: Grocery | I21: =42 -> 42
G22: Medicine | I22: =10 -> 10
G23: Chicken & Fish
G24: Water
G25: Gas | I25: 1600
G26: Office Party
G27: Sweets | I27: 288
G28: Mobile recharge | I28: =199 -> 199
C32: TOTAL EXPENSE | D32: =SUM(D3:D30) -> 155234 | G32: Total | I32: =SUM(I15:I30) -> 2972
A35: PENDING
A36: PAYMENT REASON | B36: PAYMENT CATEGORY | D36: PAYMENT AMOUNT
A38: Bangalore Expenses | B38: PERSONAL | D38: =8000 - D12 -> 5028
A41: Indranil Biye | B41: PERSONAL | D41: 2000
C68: PENDING EXPENSE | D68: =SUM(D38:D65) -> 7028
A71: Kaka | B71: PENDING | D71: =30000+16000 -> 46000
A72: Masi | B72: PENDING | D72: 25000
A73: Babu Kaka | B73: PENDING | D73: =(50000 - ('JAN-24'!D28)) -> 40000
D82: =SUM(D71:D76) -> 111000

Sheet MAY-26
A1: TOTAL EXPENSE LIST | K1: AVAILABLE FROM PREVIOUS MONTH: | L1: 2704
A2: PAYMENT REASON | B2: PAYMENT CATEGORY | C2: DATE | D2: PAYMENT AMOUNT | G2: Color Code | H2: Category | K2: INCOME IN CURRENT MONTH: | L2: 162647
A3: CC Bill (SBI) | B3: CC | C3: Online | D3: 18982 | H3: Bills & EMI
A4: CC Bill (AXIS-1) | B4: CC | C4: Online | D4: 8621 | H4: Savings | K4: TOTAL AVAILABLE: | L4: =L1 + L2 -> 165351
A5: CC Bill (AXIS-2) | B5: CC | C5: Online | D5: 10099 | H5: Maa | K5: CURRENT AVAILABLE BALANCE: | L5: =L4 - (D32) -> 5479
A6: Savings | D6: =46150-D19 -> 31150 | H6: Personal | K6: EXPECTED AVAILABLE BALANCE: | L6: =L5 - D68 + (SUMIFS(D2:D30, B2:B30, "=TEMP")) -> -2521
A7: Electricity (HOME) | B7: BILL | C7: Online | D7: 1615 | H7: Temp
A8: SIP Temp | B8: TEMP1 | C8: Online | D8: 2500 | H8: Family
A9: SIP | B9: SAVINGS | C9: Online | D9: 5500
A10: Family | B10: FAMILY | C10: Online | D10: 27000
A11: Cook | B11: FAMILY | C11: Online | D11: 4000
A12: Maa | B12: Maa | C12: Online | D12: 4000
A13: Arghya | B13: PERSONAL | C13: Online | D13: 1529 | G13: Personal Expenses
A14: Bangalore Expense | B14: PERSONAL | C14: Online | D14: =I32 -> 182 | G14: Type | H14: Date | I14: Amount
A15: Office (Puja Wedding) | B15: SOCIAL | C15: Online | D15: 500 | G15: Food
A16: Flat rent | B16: BANGALORE | C16: Online | D16: 20000 | G16: Company Food
A17: CC Bill (HDFC) | B17: CC | C17: Online | D17: 6372 | G17: Rapido
A18: UCO Bank | B18: EMI | C18: Online | D18: 500 | G18: Refreshment | I18: =20+27 -> 47
A19: Sidhu pishemosai | D19: 15000 | G19: FoodBook
A20: Electricity (FLAT) | B20: BILL | C20: Online | D20: 751 | G20: Misc | I20: =25+110 -> 135
A21: Airport Taxy | D21: 1571 | G21: Grocery
G22: Medicine
G23: Chicken & Fish
G24: Water
G25: Gas
G26: Office Party
G27: Sweets
G28: Mobile recharge
C32: TOTAL EXPENSE | D32: =SUM(D3:D30) -> 159872 | G32: Total | I32: =SUM(I15:I30) -> 182
A35: PENDING
A36: PAYMENT REASON | B36: PAYMENT CATEGORY | D36: PAYMENT AMOUNT
A38: Bangalore Expenses | B38: PERSONAL | D38: =8000 -> 8000
C68: PENDING EXPENSE | D68: =SUM(D38:D65) -> 8000
A71: Kaka | B71: PENDING | D71: =30000+16000 -> 46000
A72: Masi | B72: PENDING | D72: 25000
A73: Babu Kaka | B73: PENDING | D73: =(50000 - ('JAN-24'!D28)) -> 40000
D82: =SUM(D71:D76) -> 111000

Sheet JUN-26
A1: TOTAL EXPENSE LIST | K1: AVAILABLE FROM PREVIOUS MONTH: | L1: 1895
A2: PAYMENT REASON | B2: PAYMENT CATEGORY | C2: DATE | D2: PAYMENT AMOUNT | G2: Color Code | H2: Category | K2: INCOME IN CURRENT MONTH: | L2: 262092
A3: CC Bill (SBI) | B3: CC | C3: Online | D3: 48877 | H3: Bills & EMI
A4: CC Bill (AXIS-1) | B4: CC | C4: Online | D4: 4972 | H4: Savings | K4: TOTAL AVAILABLE: | L4: =L1 + L2 -> 263987
A5: CC Bill (AXIS-2) | B5: CC | C5: Online | D5: 8777 | H5: Maa | K5: CURRENT AVAILABLE BALANCE: | L5: =L4 - (D32) -> 25547
A6: Cook | B6: FAMILY | C6: Online | D6: 4000 | H6: Personal | K6: EXPECTED AVAILABLE BALANCE: | L6: =L5 - D68 + (SUMIFS(D2:D30, B2:B30, "=TEMP")) -> -1229
A7: Maa | B7: Maa | C7: Online | D7: 6000 | H7: Temp
A8: Family | B8: FAMILY | C8: Online | D8: 25000 | H8: Family
A9: Maa CheckUp | B9: FAMILY | C9: Online | D9: 7000
A10: Bangalore Expense | B10: PERSONAL | C10: Online | D10: =I32 -> 1424
A11: Arghya | B11: PERSONAL | C11: Online | D11: 275
A12: Savings | B12: SAVINGS | C12: Online | D12: 77000
A13: SIP Temp | B13: TEMP1 | C13: Online | D13: 2500 | G13: Personal Expenses
A14: SIP | B14: SAVINGS | C14: Online | D14: 5500 | G14: Type | H14: Date | I14: Amount
A15: Masi | B15: PENDING | C15: Online | D15: 25000 | G15: Food
A16: Flat rent | B16: BANGALORE | C16: Online | D16: 20000 | G16: Company Food
A17: Electricity (HOME) | B17: BILL | C17: Online | D17: 1615 | G17: Rapido | I17: =40+243+173 -> 456
A18: UCO Bank | B18: EMI | C18: Online | D18: 500 | G18: Refreshment
G19: FoodBook
G20: Misc | I20: =134 -> 134
G21: Grocery | I21: =65+55+224 -> 344
G22: Medicine
G23: Chicken & Fish | I23: =380 -> 380
G24: Water | I24: =110 -> 110
G25: Gas
G26: Office Party
G27: Sweets
G28: Mobile recharge
C32: TOTAL EXPENSE | D32: =SUM(D3:D30) -> 238440 | G32: Total | I32: =SUM(I15:I30) -> 1424
A35: PENDING
A36: PAYMENT REASON | B36: PAYMENT CATEGORY | D36: PAYMENT AMOUNT
A38: Bangalore Expenses | B38: PERSONAL | D38: =9000-D10 -> 7576
A39: Ekata Tournament | D39: 10000
A41: Electricity (FLAT) | B41: BILL | C41: Online | D41: 900
A42: CC Bill (HDFC) | B42: CC | C42: Online | D42: 8300
C68: PENDING EXPENSE | D68: =SUM(D38:D65) -> 26776
A71: Kaka | B71: PENDING | D71: =30000+16000 -> 46000
A73: Babu Kaka | B73: PENDING | D73: =(50000 - ('JAN-24'!D28)) -> 40000
D82: =SUM(D71:D76) -> 86000

Sheet JUL-26
A1: TOTAL EXPENSE LIST | K1: AVAILABLE FROM PREVIOUS MONTH: | L1: 2704
A2: PAYMENT REASON | B2: PAYMENT CATEGORY | C2: DATE | D2: PAYMENT AMOUNT | G2: Color Code | H2: Category | K2: INCOME IN CURRENT MONTH: | L2: 162647
H3: Bills & EMI
H4: Savings | K4: TOTAL AVAILABLE: | L4: =L1 + L2 -> 165351
H5: Maa | K5: CURRENT AVAILABLE BALANCE: | L5: =L4 - (D32) -> 165351
H6: Personal | K6: EXPECTED AVAILABLE BALANCE: | L6: =L5 - D68 + (SUMIFS(D2:D30, B2:B30, "=TEMP")) -> 20696
H7: Temp
H8: Family
G13: Personal Expenses
G14: Type | H14: Date | I14: Amount
G15: Food
G16: Company Food
G17: Rapido
G18: Refreshment | I18: =20+27 -> 47
G19: FoodBook
G20: Misc | I20: =25+110 -> 135
G21: Grocery
G22: Medicine
G23: Chicken & Fish
G24: Water
G25: Gas
G26: Office Party
G27: Sweets
G28: Mobile recharge
C32: TOTAL EXPENSE | D32: =SUM(D22:D30) -> 0 | G32: Total | I32: =SUM(I15:I30) -> 182
A35: PENDING
A36: PAYMENT REASON | B36: PAYMENT CATEGORY | D36: PAYMENT AMOUNT
A38: Bangalore Expenses | B38: PERSONAL | D38: =8000 -> 8000
A39: CC Bill (SBI) | B39: CC | C39: Online | D39: 18982
A40: CC Bill (AXIS-1) | B40: CC | C40: Online | D40: 4981
A41: CC Bill (AXIS-2) | B41: CC | C41: Online | D41: 8826
A43: Electricity (HOME) | B43: BILL | C43: Online | D43: 1615
A44: SIP Temp | B44: TEMP1 | C44: Online | D44: 2500
A45: SIP | B45: SAVINGS | C45: Online | D45: 5500
A46: Family | B46: FAMILY | C46: Online | D46: 27000
A47: Cook | B47: FAMILY | C47: Online | D47: 4000
A48: Maa | B48: Maa | C48: Online | D48: 4000
A49: UCO Bank | B49: EMI | C49: Online | D49: 500
A50: Arghya | B50: PERSONAL | C50: Online | D50: 0
A52: Flat rent | B52: BANGALORE | C52: Online | D52: 51000
... A56: Electricity (FLAT) | B56: BILL | C56: Online | D56: 751
C68: PENDING EXPENSE | D68: =SUM(D38:D65) -> 144655
A71: Kaka | B71: PENDING | D71: =30000+16000 -> 46000
A72: Masi | B72: PENDING | D72: 25000
A73: Babu Kaka | B73: PENDING | D73: =(50000 - ('JAN-24'!D28)) -> 40000
D82: =SUM(D71:D76) -> 111000

Sheet TEMP
A1: 94000
A3: Electricity | B3: 4000
A4: Gas | B4: 3000
A5: Groccery | B5: 7000
A6: Rice & Atta | B6: 4000
A7: Maa | B7: 15000
A8: iAloy | B8: 3000
A9: In hand | B9: 2000
A12: SIPs
A13: Current | B13: 5000
A14: Roni Biye | B14: 10000
A15: Rini Biye | B15: 5000 | F15: Saving | G15: =SUM(B13:B24) -> 44000
A16: bari | B16: 10000
A17: Savings | B17: 6000
A18: Mediclaim | B18: 3000
A19: lic | B19: 5000
A26: TOTAL | B26: =SUM(B3:B24) -> 82000
A27: IN HAND | B27: =A1-B26 -> 12000
